Workbook
Name Percepcion: SIAP!$T$41:$T$54
Name Retencion: SIAP!$T$61:$T$138

Sheet Panel BOT
B3: PANEL DE PROCESO
B4: Nombre Declaracion | C4: Procesa (SI/NO)
B5: ACTIVO | C5: NO
B6: PASIVO | C6: NO
B7: PATRIMONIO | C7: NO
B8: RESULTADOS | C8: NO
B9: Rtdo contable s.fuente | C9: NO
B10: IDyC DJ | C10: NO
B11: IDyC Anticipos | C11: NO
B12: RETEN. Y PERC. | C12: NO
B13: PERC. ADUANERO RG3577 | C13: NO
B14: OTROS | C14: NO
B15: Ajustes Fuente Argentina | C15: NO
... B18: Quebrantos F.E. | C18: NO

Sheet Datos descriptivos
F2: Datos Descriptivos - Modificando Declaración Jurada
M3: CUADROS CHICOS SON PARA TILDE
F4: Datos de la Declaración Jurada | M4: EMPRESA: | N4: =IF(ACTIVO!D2=0,"",ACTIVO!D2) | P4: =ACTIVO!E2 -> CUIT:
F7: Año Fiscal | I7: Original/Rect. | M7: Cantidad de meses | P7: Mes de Cierre | S7: Establecimiento
E11: Ejercicio Fiscal Irregular | H11: (COMPLETAR CON UNA X SOLO EN CASO QUE CORRESPONDA EJERCICIO IRREGULAR Y COMPLETAR TODOS LOS DATOS DEL RECUADRO)
F14: Es primer ejercicio? | M14: Es irregular por cese de actividad? | S14: Es irregular por cambio de cierre?
F16: Fecha de Inicio del Período Fiscal que declara | N16: Fecha de Finalización del Período Fiscal que declara
I21: (COMPLETAR CON UNA X SOLO EN CASO QUE CORRESPONDA Y COMPLETAR CUIT DEBAJO) | P21: Zona de Emergencia Agropecuaria
F22: Es empresa continuadora?
P23: Zona de Desastre Agropecuario
F24: CUIT Empresa Antecesora
P25: Utiliza Beneficios de amortización Acelerada
G29: (COMPLETAR EL PRIMERO O EL SEGUNDO EN CASO DE CORRESPONDER) | P29: Entidad exenta
P31: Estabilidad Fiscal | R31: Norma Estabilidad Fiscal
F32: Empresa Promovida | G32: Cantidad de Proyectos | K32: Sistema de | O32: (EN CASO DE MARCAR ESTA OPCION COMPLETAR NORMA)
K33: Registración Utilizado | M33: Manual | R33: CUIT/L del contador
P35: Se encuentra encuadrado en el RIGI?
E36: Transferencia de Tecnología %
P37: Es RIGI primer Ejercicio?
E42: Tipo de Vinculación: | I42: Vinculación con empresas nacionales | M42: Vinculación con empresas internacionales | P42: Ninguna
E44: Origen de la Renta: | I44: Renta de Fuente Argentina | M44: Renta de Fuente Extranjera
E46: Esta obligado a presentar DJ por haber realizado:
F48: Está obligado a presentar DJ por haber realizado:
F50: Operaciones internacionales con sujetos vinculados o radicados en países de nula o baja tributación.
F52: Operaciones de exportación e importación de Bienes entre Sujetos Independientes a cuyo respecto pueda establecerse el precio internacional de público y notorio conocimiento a través de mercados transparentes, bolsas de comercio o similares.
F55: Operaciones de exportación e importación de Bienes entre Sujetos Independientes por un monto anual -en su conjunto- superior a la suma de Pesos Un Millón ($1.000.000.-), a cuyo respecto no pueda establecerse el precio internacional de público y notorio conocimiento, a través de mercados transparentes, bolsas de comercio o similares.
F59: No está obligado a presentar declaración jurada por haber realizado:
F61: Operaciones de Exportación de Importación de Bienes entre Sujetos Independientes, a cuyo respecto no pueda establecerse el precio internacional de público y notorio conocimiento a través de mercados transparentes, bolsas de comercio o similares por un monto anual en su conjunto inferior a la suma de Pesos Un Millón ($1.000.000.-)
E65: Certificado de Residencia: | I65: Solicitó Certificado de Residencia?
F69: Alicuota del impuesto | K69: Se abonará el Gravamen empleando la escala correspondiente al Art. 3 de la Ley 27.630.
F71: Más datos de la Declaración Jurada
F74: ¿Aplica Normas NIIF?
F76: ¿Realizó operaciones amparadas por algún convenio para evitar la doble imposición internacional?
F78: ¿Percibió rentas exentas y/o no alcanzadas por aplicación de convenios para evitar la Doble Imposición Intenacional?
F80: ¿Percibió Ingresos por juegos de azar y apuestas?

Sheet ACTIVO
C1: v1.1 | G1: ACTIVO
C2: EMPRESA: | E2: CUIT: | G2: DTT. TEAMS | H2: ¿Habilitar Fuente Extranjera?
C3: Periodo Fiscal | E3: Saldo al | G3: mazar | H3: NO
C4: Secuencia: | D4: Original
C6: RESUMEN | D6: Siap | E6: s/ DETALLE | F6: s/ BCE.PUBLICAC. | G6: DIFERENCIA
C8: ACTIVO | E8: =+G14 -> 0 | G8: =+E8-F8 -> 0
C9: PASIVO | E9: =+PASIVO!G3 -> 0 | G9: =+E9-F9 -> 0
C10: PATRIMONIO | E10: =+PATRIMONIO!F2 -> 0 | G10: =+E10-F10 -> 0
C12: RESULTADO | E12: =+RESULTADOS!D2 -> 0 | G12: =+E12-F12 -> 0
B14: TOTAL ACTIVO s/detalle | G14: =+G20+G103+G221+G447+G325+G306 -> 0
D16: Total del Activo corriente | F16: 0
D18: Total del Activo no corriente | F18: 0
C20: 1,1- Total Disponibilidades | G20: =+G22+G24+G26+G69 -> 0
D22: 1,1,1 Efectivo en moneda nacional | G22: 0
D24: 1,1,2 Cheque en cartera | G24: 0
D26: 1,1,3 Bancos | G26: =+G28+G48 -> 0
D28: 1,1,3,1-Bancos en el país | G28: =+F46 -> 0
D30: Razon Social | E30: N° CBU | F30: =+$E$3 -> Saldo al
D46: TOTAL BANCOS Y CORRESPONSALES DEL PAIS | F46: =SUM(F31:F45) -> 0
D48: 1,1,3,2-Bancos del exterior | G48: =+G67 -> 0
D50: Nombre de la Entidad | E50: CUIT PAIS | F50: N° de Cuenta | G50: =+F30 -> Saldo al
D67: TOTAL BANCOS Y CORRESPONSALES DEL EXTRANJERO | G67: =SUM(G51:G66) -> 0
D69: 1,1,4 -Efectivo en Moneda Extranjera | G69: =+(E72*G72)+(E73*G73)+(E74*G74)+(E75*G75)+(E76*G76)+(E77*G77)+(E78*G78)+(E79*G79) -> 0
D71: Tipo de Moneda | E71: Cotización | F71: Fecha Cotización | G71: Cantidad
D80: TOTAL EFECTIVO EN MON.EXTRANJERA
D83: 1,1,5 - Cuentas de Pago PSP | G83: =G101 -> 0
D85: CUIT | E85: Nombre de la Billetera | F85: N° de CVU | G85: Saldo al Cierre del Ejercicio
D101: TOTAL CUENTAS DE PAGO PSP | G101: =SUM(G86:G100) -> 0
C103: 1,2- Bienes de Uso | G103: =+G105+G137+G165+G195 -> 0
D105: 1,2,1 Inmuebles | G105: =+G107+G109+G111-G113-G115 -> 0
E107: Inmuebles al Inicio Netos de Amortizaciones Acumuladas
E109: Ajuste | G109: 0
E111: Altas de Ejercicio
E113: Bajas de Ejercicio
E115: Amortizacion Inmueble
D118: 1,2,1,2 Detalle de inmuebles
D120: Mes y año de Adquisicion (MM-AAAA) | E120: Porcentaje de participacion | F120: Tipo | G120: Destino | H120: Calle | I120: Número | J120: Piso | K120: Dpto/Of. | L120: Localidad | M120: Codigo postal | N120: Provincia | O120: Catastro | P120: Amortizacion Acelerada Segun Ley Nro | Q120: Amortización del periodo | R120: Valuacion Fiscal | S120: Valuacion S/ Impuesto a las Ganancias | T120: Importe Amortización Acelerada del Periodo
D137: 1,2,2 Rodados | G137: =+G139+G141+G143-G145-G147 -> 0
E139: Rodados al inicio neros de amortizaciones acumuladas
E141: Ajuste | G141: 0
E143: Altas de Ejercicio
E145: Bajas de Ejercicio
E147: Amortizaciones Rodados
D150: 1,2,2,1 Detalle de Rodados al Cierre
D152: Mes y año de Adquisicion (MM-AAAA) | E152: Porcentaje de participacion | F152: Patente | G152: Marca | H152: Modelo | I152: Fabrica | J152: Año de Fabricacion | K152: Amortizacion Acelerada segun Ley Nro | L152: Importe Amortizacion del Periodo | M152: Valuacion Segun Impuesto a las Ganancias | N152: Importe Amortización Acelerada del Periodo
L163: =+SUM(L153:L162) -> 0
D165: 1,2,3 Total de Instalaciones | G165: =+G167+G169+G171-G173-G175 -> 0
E167: Instalaciones al Inicio neto de amortizaciones acumuldas
E169: Ajuste
E171: Altas de Ejercicio
E173: Bajas de Ejercicio
E175: Amortización Instalaciones | G175: 0
D179: 1,2,3,1 Detalle de Instalaciones
D186: Descripción del bien | E186: Fecha de incorporación al patrimonio (MM/AAAA) | F186: Amortizacion Acelerada según Ley Nro. | G186: Importe Amortizacion del periodo | H186: Valuacion Segun Impuesto a las Ganancias | I186: Importe Amortización Acelerada del Periodo
F193: =+SUM(F187:F192) -> 0 | G193: =+SUM(G187:G192) -> 0
D195: 1,2,4 Otros Bienes de Uso | G195: =+G197+G199-G201+G203-G205 -> 0
E197: Otros Bienes de Uso al inicio neto de amortizaciones acumuladas
E199: Altas de Ejercicio
E201: Bajas de Ejercicio
E203: Ajuste
E205: Amortizacion otros bienes de uso | G205: =+G215 -> 0
D207: 1,2,4,1 Detalle otros bienes de uso
E209: Descripción del bien
E211: Fecha de incorporación al patrimonio (DD/MM/AAAA)
E213: Amortizacion Acelerada Segun Ley Nro
E215: Importe amortizacion del periodo
E217: Importe Amortización Acelerada del Periodo
E219: Valuacion Segun Impuesto a las Ganancias
C221: 1,3 - Inversiones | G221: =+G223+G236+G247+G258+G267+G277+G287+G289+G291+G293+G295+G297 -> 0
D223: 1,3,1 Acciones | G223: =+G234 -> 0
C225: Descripcion | D225: Denominación | F225: Clase | G225: Valor
C234: Total | G234: =+SUM(G226:G233) -> 0
D236: 1,3,2 Titulos Públicos | G236: =+G245 -> 0
C238: Descripcion | D238: Denominación | F238: Clase | G238: Valor
C245: Total | G245: =+SUM(G239:G244) -> 0
D247: 1,3,3 Total de Obligaciones | G247: =+G256 -> 0
C249: Descripcion | D249: Denominación | F249: Clase | G249: Valor
C256: Total | G256: =+SUM(G250:G255) -> 0
D258: 1,3,4 Total de Cupones | G258: =+G265 -> 0
C260: Descripcion | E260: Denominación | G260: Valor
C265: Total | G265: =+SUM(G261:G264) -> 0
D267: 1,3,5 Total de Fondos Comunes | G267: =+G275 -> 0
C269: Descripcion | E269: Denominación | G269: Valor
C275: Total | G275: =+SUM(G270:G274) -> 0
D277: 1,3,6 Total de Otras Inversiones | G277: =+F285 -> 0
D279: Descripción | E279: Valor | F279: Valor
D285: Total | F285: =+SUM(F280:G284) -> 0
D287: 1,3,7 Inmuebles | G287: 0
D289: 1,3,8 Forestales | G289: 0
D291: 1,3,9 Agrícola Ganadera | G291: 0
D293: 1,3,10 Otros | G293: 0
D295: 1,3,11 Previsiones | G295: 0
D297: 1,3,12 Detalle de Inversiones Sociedad controlada, controlante y vinculadas | G297: =+G302 -> 0
D299: Nombre y Apellido, Denominación o Razón Social | E299: N° C.U.I.T. | G299: Saldo al cierre
D302: TOTAL INV.SOC. CONTROLADA, CONTROLANTE Y/O VINCULADA | G302: =+SUM(G300:G301) -> 0
C306: 1,4 - Bienes Intangibles | G306: =+G308+G310+G312-G314-G316-G318 -> 0
E308: Intangibles amortizables al Inicio Netos de Amortizaciones Acumuladas
E310: Ajuste
E312: Altas de Ejercicio
E314: Amortización intangibles amortizables
...

Sheet SIAP
A2: BANCOS | C2: CUIT PAIS | E2: IDYC | H2: tipo de moneda | J2: Acciones | L2: TITULOS PUBLICOS | N2: OBLIGACIONES | P2: CUPONES | R2: fci | T2: AMORT ACELERADA | V2: REGIMEN
A3: ACONCAGUA COOP.LTDO. | C3: AFGANISTAN | D3: CBU | E3: Percepción bancaria sobre los Créditos y Débitos | F3: Percepción bancaria o Ingreso propio | H3: Afgani afgano | J3: AGROMETAL S.A.I. // ordinarias escriturales (1 voto) | L3: BONO ACONCAGUA - PCIA.MENDOZA // 2007 | N3: ACTUAL S.A. // SERIE II | P3: BONOS EXTERNOS 1992 - CUPON DÓLAR U$S | R3: 1810 AHORRO | T3: Ninguna Ley de amortización acelerada | V3: 531 Import. def. bs. para venta - art. 40 1er párrafo
A4: AGENCIA DE CAMBIO GOMEZ S.R.L. | C4: ALEMANIA, REP. FED. | D4: CVU | E4: DDJJ | F4: DDJJ | H4: Baht tailandes | J4: ALPARGATAS S.A.I. y C. // ordinarias escriturales (1 voto) u$s cable | L4: BONO ACONCAGUA - PCIA.MENDOZA // 2007 - dólar (u$s) | N4: ACTUAL S.A. // SERIE V | P4: PRO2 CUPON IMPAGO VTO. 02.01.02 | R4: 1810 MAS AHORRO | T4: Nº 24.196 Inversiones Mineras | V4: 080 Importación definitiva de bienes con C.V.D.I.
A5: ALAS COOP.LTDO. | C5: ANGUILA (Territorio no autónomo del Reino Unido) | H5: Balboa panameña | J5: ALPARGATAS S.A.I. y C. // ordinarias escriturales (1 voto) | L5: BONO ACONCAGUA - PCIA.MENDOZA // 2007 - u$s cable | N5: AEROPUERTOS ARGENTINA 2000 S.A. // GARANTIZADAS AERAO | P5: PRO1 CUPON IMPAGO VTO. 02.01.02 | R5: 1810 RENTA FIJA ARGENTINA | T5: Nº 25.080 Ley de Inversiones para bosques cultivados | V5: 081 Importación definitiva de bienes para uso de importador con C.V.D.I.
A6: ALHEC TOURS S.A. CAMBIO BOLSA Y TURISMO | C6: ANTIGUA Y BARBUDA (Estado independiente) | E6: Impuesto | H6: Birr etiope | J6: ALTO PALERMO SHOPPING ARGENTINO S.A. // ordinarias escriturales (1 voto) u$s cable | L6: BONO DE CANC.DE DEUDAS (PROVINCIA DE FORMOSA) LEY 1184 // primera serie | N6: AEROPUERTOS ARGENTINA 2000 S.A. // GARANTIZADAS OAEY1 | P6: PRE4 CUPON IMPAGO VTO. 02.01.02 | R6: 1810 RENTA VARIABLE ARGENTINA | T6: Nº 25.922 Ley de Promoción de la Industria del Software | V6: 082 Importación definitiva de bienes para uso de importador sin C.V.D.I.
A7: ALIANZA ROSARIO COOP.LTDO. | C7: ANTILLAS HOLANDESAS (Territorio de Países Bajos) | E7: Ganancias Personas Jurídicas | H7: Bolivar venezolano | J7: ALTO PALERMO SHOPPING ARGENTINO S.A. // ordinarias escriturales (1 voto) | L7: BONO DE CANC.DE DEUDAS (PROVINCIA DE FORMOSA) LEY 1184 // primera serie dólar (u$s) | N7: AEROPUERTOS ARGENTINA 2000 S.A. // GARANTIZADAS U$S CABLE | P7: PRE3 CUPON IMPAGO VTO. 02.01.02 | R7: 1822 RAICES AHORRO PESOS | T7: Nº 25.924 Inversiones en Bienes de Capital nuevos y obras de infraestructura | V7: 083 Importación definitiva de bienes sin C.V.D.I.
A8: AMERICAN EXPRESS BANK LTD. S.A. | C8: ARABIA SAUDITA | E8: Ganancias Personas Físicas | H8: Boliviano | J8: ALUAR ALUMINIO ARGENTINO S.A.I. y C. // ordinarias escrit (1 voto) u$s cable | L8: BONO DE CANC.DE DEUDAS (PROVINCIA DE FORMOSA) LEY 1184 // primera serie u$s cable | N8: AEROPUERTOS ARGENTINA 2000 S.A. // OBLIGACIONES NEGOCIABLES CLASE A | P8: PRO3 CUPON IMPAGO VTO. 28.12.02 | R8: 1822 RAICES DOLARES PLUS CLASE A | T8: Nº 26.093 Régimen de Regulación y Promoción para la Producción y Uso Sustentables de Biocombustibles | V8: 864 Operaciones de exportación definitiva para consumo
A9: ANDINA INTERNACIONAL CAMBIO Y TURISMO S. | C9: ARCHIPIELAGO DE SVBALBARD | E9: Ganancia Mínima Presunta | H9: Bosnia-Herzegovina | J9: ALUAR ALUMINIO ARGENTINO S.A.I. y C. // ordinarias escrit (1 voto) | L9: BONO DE LA NACION ARGENTINA EN DOLARES ESTADOUNIDENSES // 5,75% VENC.2025 AA25 | N9: AES ARGENTINA GENERACIÓN S.A. // CLASE A | P9: PRO4 CUPON IMPAGO VTO. 28.12.01 | R9: 1822 RAICES DOLARES PLUS CLASE B | T9: Nº 26.123 Promoción del Hidrógeno | V9: 588 Ganancias. Percepcion Aduanera Metales Preciosos. RG 5815
A10: ANTONIO DI GIORGIO S.A., CAMBIOS Y TURIS | C10: ARGELIA | H10: Cedi ghanés | J10: ANDES ENERGIA PLC. // ordinarias (1 voto) | L10: BONO DE LA NACION ARGENTINA EN DOLARES ESTADOUNIDENSES // 5,75% VENC.2025 AA25X | N10: AGROEMPRESA COLON S.A. // SIMPLES | P10: PRO5 CUPON IMPAGO VTO. 15.01.02 | R10: 1822 RAICES INVERSION | T10: Nº 26.154 Regímenes promocionales para la exploración y explotación de hidrocarburos
A11: ARG DEL ATLANTICO S.A. | C11: ARMENIA | H11: Chelin keniata | J11: ANGEL ESTRADA Y CIA. S.A.I // ordinarias escriturales a (5 votos) | L11: BONO DE LA NACION ARGENTINA EN DOLARES ESTADOUNIDENSES // 5,75% VENC.2025 DÓLAR U$S | N11: AGROEMPRESA COLON S.A. // SIMPLES DÓLAR U$S | P11: PRO6 CUPON IMPAGO VTO. 15.01.02 | R11: 1822 RAICES RENTA EN PESOS | T11: Nº 26.190 Régimen de Fomento Nacional para el uso de fuentes renovables de energía destinada a la producción de energía eléctrica
A12: ARGECAM S.R.L. | C12: ARUBA (Territorio de Países Bajos) | E12: Tipo de contrato | H12: Chelin somali | J12: ANGEL ESTRADA Y CIA. S.A.I // ordinarias escriturales b (1 voto) | L12: BONO DE LA NACION ARGENTINA EN DOLARES ESTADOUNIDENSES // 5,75% VENC.2025 U$S CABLE AA25C | N12: AGROFINA S.A. // CLASE I SERIE II | P12: PRO9 CUPON IMPAGO VTO. 15.01.02 | R12: 1822 RAICES RENTA GLOBAL | T12: Nº 26.270 Promoción del desarrollo y producción de la biotecnología moderna
A13: AVELLANEDA S.A. | C13: ASCENCION | E13: FORWARD COMPRADO | H13: Chelin tanzano | J13: AUTOPISTAS DEL SOL S.A. // ordinarias escriturales d 1 voto u$s cable | L13: BONO DE LA NACION ARGENTINA EN DOLARES ESTADOUNIDENSES // 5,75% VENC.2025 U$S CABLE AA25Z | N13: AGROFINA S.A. // CLASE II | P13: PR10 CUPON IMPAGO VTO. 15.01.02 | R13: 1822 RAICES VALORES FIDUCIARIOS | T13: Nº 26.360 Promoción de inversiones en Bienes de Capital y Obras de Infraestructura
A14: BACS BANCO DE CREDITO Y SECURITIZACION S.A. | C14: AUSTRALIA | E14: FORWARD VENDIDO | H14: Chelin ugandes | J14: AUTOPISTAS DEL SOL S.A. // ordinarias escriturales d 1 voto | L14: BONO DE LA NACION ARGENTINA EN DOLARES ESTADOUNIDENSES // 7% 2017 - BONAR X AA17X | N14: AGROFINA S.A. // CLASE III | P14: BCMR CUPON IMPAGO VTO.1.11.01 | R14: 1822 RAICES VALORES NEGOCIABLES | T14: N° 27.541 Ley de Solidaridad Social - Beneficio cumplidores
A15: BANCA NAZIONALE DEL LAVORO S.A. | C15: AUSTRIA | E15: FUTURO COMPRADO | H15: Colón costarricense | J15: BANCO DE GALICIA Y BS.AS. S.A. // ordinarias escriturales a (5 votos) | L15: BONO DE LA NACION ARGENTINA EN DOLARES ESTADOUNIDENSES // 7% 2017 - BONAR X AA17 | N15: AGROFINA S.A. // CLASE IV | P15: BCFD1 CUPON IMPAGO VTO. 03.12.01 | R15: ADCAP ABIERTO LEY 27260 - CLASE A | T15: N° 27.653 Ley de Alivio Fiscal
A16: BANCO 1784 S.A. | C16: AZERBAIDZHAN | E16: FUTURO VENDIDO | H16: Colon El Salvador | J16: BANCO DE GALICIA Y BS.AS. S.A. // ordinarias escriturales b (1 voto) u$s cable | L16: BONO DE LA NACION ARGENTINA EN DOLARES ESTADOUNIDENSES // 7% 2017 - BONAR X DÓLAR (U$S) AA17Y | N16: AGROFINA S.A. // CLASE IV DÓLAR U$S | P16: SALD1 CUPON IMPAGO VTO. 03.12.01 | R16: ADCAP ABIERTO LEY 27260 - CLASE B | T16: N° 27.686 Ley de Promoción de Inveriones en la Ind. Automotriz y su cadena de valor
A17: BANCO ACCION COOP.LTDO. | C17: BANGLADESH | E17: OPCIÓN LANZADA DE COMPRA | H17: Compuesto Unidad Europea (EURCO) | J17: BANCO DE GALICIA Y BS.AS. S.A. // ordinarias escriturales b (1 voto) | L17: BONO DE LA NACION ARGENTINA EN DOLARES ESTADOUNIDENSES // 7% 2017 - BONAR X DÓLAR (U$S) AA17D | N17: AGROFINA S.A. // CLASE IV U$S CABLE | P17: BCDF1 CUPON IMPAGO VTO. 03.12.01 | R17: ADCAP ABIERTO LEY 27260 - CLASE C | T17: Otra
A18: BANCO ACISO COOPERATIVO LTDO. ROSARIO | C18: BARBADOS (Estado independiente) | E18: OPCIÓN LANZADA DE VENTA | H18: Cordoba nicaraguense | J18: BANCO HIPOTECARIO S.A. // ords escrit d (3 votos) cotizables u$s cable | L18: BONO DE LA NACION ARGENTINA EN DOLARES ESTADOUNIDENSES // 7% 2017 - BONAR X U$S CABLE AA17C | N18: AGROFINA S.A. // CLASE V | P18: SALT1 CUPON IMPAGO VTO. 03.12.01 | R18: ADCAP ABIERTO LEY 27260 - CLASE D
A19: BANCO AGRARIO COM. E IND.DE SAN JUAN S.A. | C19: BELGICA | E19: OPCIÓN ADQUIRIDA DE COMPRA | H19: Corona danesa | J19: BANCO HIPOTECARIO S.A. // ords escriturales d (3 votos) - cotizables | L19: BONO DE LA NACION ARGENTINA EN DOLARES ESTADOUNIDENSES // 7% 2017 - BONAR X U$S CABLE AA17Z | N19: AGROFINA S.A. // CLASE VI | P19: BCOR2 CUPON IMPAGO VTO. 02.01.02 | R19: ADCAP ABIERTO LEY 27260 - CLASE E
A20: BANCO ALIANCOOP COOP.LTDO. | C20: BELICE (Estado independiente) | E20: OPCIÓN ADQUIRIDA DE VENTA | H20: Corona eslovaca | J20: BANCO MACRO S.A. // ordinarias escriturales a (5 votos) | L20: BONO DE LA NACION ARGENTINA EN DOLARES ESTADOUNIDENSES // 7,625% VENC. 2037 AA37 | N20: ALBANESI S.A. // CLASE I | P20: BCOR1 CUPON IMPAGO VTO. 02.01.02 | R20: ADCAP ABIERTO LEY 27260 - CLASE F | T20: MES
A21: BANCO ALMAFUERTE COOPERATIVO LIMITADO | C21: BENIN | E21: STOCK OPTION | H21: Corona estonia | J21: BANCO MACRO S.A. // ordinarias escriturales b (1 voto) u$s cable | L21: BONO DE LA NACION ARGENTINA EN DOLARES ESTADOUNIDENSES // 7,625% VENC. 2037 AA37X | N21: ALBANESI S.A. // CLASE II | P21: BCFD1 CUPON IMPAGO VTO. 02.01.02 | R21: ADCAP GLOBAL CLASE A | T21: 01-
A22: BANCO ALVAREZ COOP.LTDO. SANTA FE | C22: BERMUDAS (Territorio no autónomo del Reino Unido) | E22: OTROS | H22: Corona noruega | J22: BANCO MACRO S.A. // ordinarias escriturales b (1 voto) | L22: BONO DE LA NACION ARGENTINA EN DOLARES ESTADOUNIDENSES // 7,625% VENC. 2037 DÓLAR U$S | N22: ALGABO S.A. // SERIE I CLASE I | P22: BOHI1 CUPON IMPAGO VTO.02.01.02 | R22: ADCAP GLOBAL CLASE B | T22: 02-
A23: BANCO ARGENCOOP COOPERATIVO LIMITADO | C23: BIELORUSIA | E23: SWAP | H23: Corona sueca | J23: BANCO PATAGONIA S.A. // ordinarias clase b (1 voto) u$s cable | L23: BONO DE LA NACION ARGENTINA EN DOLARES ESTADOUNIDENSES // 7,625% VENC. 2037 U$S CABLE | N23: ANGEL ESTRADA Y CIA. S.A. // CLASE III | P23: BORD1 CUPON IMPAGO VTO. 02.01.02 | R23: ADCAP GLOBAL CLASE I | T23: 03-
A24: BANCO ARGENFE S.A. | C24: BOLIVIA | H24: Dalasi gambiano | J24: BANCO PATAGONIA S.A. // ordinarias clase b (1 voto) | L24: BONO DE LA NACION ARGENTINA EN DOLARES ESTADOUNIDENSES // 8% 2020 (BONAR2020USD) AO20 | N24: ARAUCO ARGENTINA S.A. // SIMPLES CLASE 1 | P24: BORN1 CUPON IMPAGO VTO. 02.01.02 | R24: ADCAP RENTA MIXTA CLASE A | T24: 04-
A25: BANCO ARGENTARIA S.A. | C25: BOSNIA HERZEGOVINA | E25: Origen/Destino | H25: Denar macedonio | J25: BANCO SANTANDER RIO S.A. // ordinarias escriturales b (1 voto) u$s cable | L25: BONO DE LA NACION ARGENTINA EN DOLARES ESTADOUNIDENSES // 8% 2020 (BONAR2020USD) AO20X | N25: ARCOR S.A.I.C. // CLASE 11 | P25: RC21 CUPON IMPAGO VTO. 02.01.02 | R25: ADCAP RENTA MIXTA CLASE B | T25: 05-
A26: BANCO ARGENTINO DE INVERSION S.A. | C26: BOTSWANA | E26: ALTA / BAJA | H26: Derechos especiales de giro | J26: BANCO SANTANDER RIO S.A. // ordinarias escriturales b (1 voto) | L26: BONO DE LA NACION ARGENTINA EN DOLARES ESTADOUNIDENSES // 8% 2020 (BONAR2020USD)DÓLAR U$S | N26: ARCOR S.A.I.C. // CLASE 7 | P26: BCDF1 CUPON IMPAGO VTO. 02.01.02 | R26: AL ABIERTO Pymes CLASE A | T26: 06-
A27: BANCO ASFIN S.A. | C27: BRASIL | E27: ALTA / SIGUE | H27: Dinar algerino | J27: BANCO SANTANDER RIO S.A. // ordinarias escriturales (1 voto) dólar (u$s) | L27: BONO DE LA NACION ARGENTINA EN DOLARES ESTADOUNIDENSES // 8% 2020 (BONAR2020USD)U$S CABLE AO20C | N27: ARCOR S.A.I.C. // CLASE 8 | P27: PRO3 CUPON IMPAGO VTO.28.01.02 | R27: AL ABIERTO Pymes CLASE B | T27: 07-
A28: BANCO AUSTRAL S.A. | C28: BRUNEI DARUSSALAM (Estado independiente) | E28: VIENE / SIGUE | H28: Dinar bahreini | J28: BANCO SANTANDER RIO S.A. // ordinarias escriturales (1 voto) u$s cable | L28: BONO DE LA NACION ARGENTINA EN DOLARES ESTADOUNIDENSES // 8% 2020 (BONAR2020USD)U$S CABLE AO20Z | N28: ARCOR S.A.I.C. // CLASE 9 | P28: PRO4 CUPON IMPAGO VTO. 28.01.02 | R28: AL ABIERTO Pymes CLASE C | T28: 08-
A29: BANCO B.I. CREDITANSTALT S.A. | C29: BULGARIA | E29: VIENE / BAJA | H29: Dinar iraqi | J29: BANCO SANTANDER RIO S.A. // ordinarias escriturales (1 voto) | L29: BONO DE LA NACION ARGENTINA EN DOLARES ESTADOUNIDENSES // 8,75% 2024 (BONAR 2024) AY24X | N29: ARCOR S.A.I.C. // CLASE 9 DÓLAR U$S | P29: BCFD1 CUPON IMPAGO VTO. 29.01.02 | R29: AL AHORRO CLASE A | T29: 09-
A30: BANCO BAIRES S.A. | C30: BURKINA FASO | H30: Dinar jordano | J30: BANCO SUQUIA S.A. // ordinarias escriturales a (5 votos) | L30: BONO DE LA NACION ARGENTINA EN DOLARES ESTADOUNIDENSES // 8,75% 2024 (BONAR 2024) AY24 | N30: ARCOR S.A.I.C. // CLASE 9 U$S CABLE | P30: BCDF1 CUPON IMPAGO VTO. 29.01.02 | R30: AL AHORRO CLASE B | T30: 10-
A31: BANCO BANEX S.A. | C31: BURUNDI | E31: Vigencia | H31: Dinar Kuwaiti | J31: BANCO SUQUIA S.A. // ordinarias escriturales b (1 voto) | L31: BONO DE LA NACION ARGENTINA EN DOLARES ESTADOUNIDENSES // 8,75% 2024 (BONAR 2024) DÓLAR U$S AY24D | N31: AXION ENERGY ARGENTINA S.A. // CLASE II | P31: SALT1 CUPON IMPAGO VTO. 29.01.02 | R31: AL AHORRO PLUS CLASE A | T31: 11-
A32: BANCO BANSUD S.A. | C32: BUTAN | E32: VIGENTE | H32: Dinar libio | J32: BANCO SUQUIA S.A. // ordinarias escriturales b (1 voto) u$s cable | L32: BONO DE LA NACION ARGENTINA EN DOLARES ESTADOUNIDENSES // 8,75% 2024 (BONAR 2024) DÓLAR U$S AY24Y | N32: AXION ENERGY ARGENTINA S.A. // CLASE III | P32: BCOR2 CUPON IMPAGO VTO. 30.01.02 | R32: AL AHORRO PLUS CLASE B | T32: 12-
A33: BANCO BARRANCAS COOP.LTDO.STA FE | C33: CAMBOYA (EX KAMPUCHEA) | E33: NO VIGENTE | H33: Dinar sudanes | J33: BBVA BANCO FRANCES S.A. // ordinarias escriturales (1 voto) u$s cable | L33: BONO DE LA NACION ARGENTINA EN DOLARES ESTADOUNIDENSES // 8,75% 2024 (BONAR 2024) U$S CABLE AY24Z | N33: AXION ENERGY ARGENTINA S.A. // CLASE IV | P33: BCOR1 CUPON IMPAGO VTO. 30.01.02 | R33: AL AHORRO PLUS CLASE C
A34: BANCO BASEL S.A. | C34: CAMERUN | H34: Dinar tunecino | J34: BBVA BANCO FRANCES S.A. // ordinarias escriturales (1 voto) | L34: BONO DE LA NACION ARGENTINA EN DOLARES ESTADOUNIDENSES // 8,75% 2024 (BONAR 2024) U$S CABLE AY24C | N34: AXION ENERGY ARGENTINA S.A. // CLASE V | P34: BOHI1 CUPON IMPAGO VTO.30.01.02 | R34: AL DESARROLLO ARGENTINO CLASE A
A35: BANCO BIRCO COOP.LTDO. RUFINO STA FE | C35: CAMPIONE D@ITALIA | E35: Intencion | H35: Dinar yugoslavo | J35: BODEGAS ESMERALDA S.A. // ordinarias escriturales (1 voto) | L35: BONO DE LA NACION ARGENTINA EN DOLARES ESTADOUNIDENSES // 9% 2018 AN18 | N35: AXION ENERGY ARGENTINA S.A. // CLASE VI | P35: BORD1 CUPON IMPAGO VTO. 29.01.02 | R35: AL DESARROLLO ARGENTINO CLASE B | T35: Alicuota del impuesto
A36: BANCO BISEL SOCIEDAD ANONIMA | C36: CANADA | H36: Dirham de los Emiratos Arabes Unidos | J36: BOLDT GAMING S.A. // ordinarias escrit. (1 voto) | L36: BONO DE LA NACION ARGENTINA EN DOLARES ESTADOUNIDENSES // 9% 2018 AN18X | N36: AXION ENERGY ARGENTINA S.A. // CLASE VII | P36: BORN1 CUPON IMPAGO VTO. 29.01.02 | R36: AL DESARROLLO ARGENTINO CLASE C | T36: 0.25
A37: BANCO BRADESCO ARGENTINA SA | C37: CENTRO AFRICANO, REP. | E37: COBERTURA | H37: Dirham marroqui | J37: BOLDT S.A. // ordinarias escriturales (1 voto) u$s cable | L37: BONO DE LA NACION ARGENTINA EN DOLARES ESTADOUNIDENSES // 9% 2018 DÓLAR (U$S) AN18D | N37: BACS BANCO DE CREDITO Y SECURITIZACION S.A. // CLASE IX | P37: PRO2 CUPON IMPAGO VTO. 01.02.02 | R37: AL DIVERSIFICADO CLASE A | T37: 0.3
A38: BANCO BRAGADO COOP.LTDO. | C38: CHAD | E38: DISTINTO DE COBERTURA | H38: Dobra de Santo Tone y Principe | J38: BOLDT S.A. // ordinarias escriturales (1 voto) | L38: BONO DE LA NACION ARGENTINA EN DOLARES ESTADOUNIDENSES // 9% 2018 U$S CABLE AN18C | N38: BACS BANCO DE CREDITO Y SECURITIZACION S.A. // CLASE VI | P38: PRO1 CUPON IMPAGO VTO. 29.01.02 | R38: AL DIVERSIFICADO CLASE B | T38: 0.35
A39: BANCO CABILDO S.A. | C39: CHECA, REPUBLICA | H39: Dolar Australiano | J39: CAMUZZI GAS PAMPEANA S.A. // ordinarias escriturales clase b (1 voto) - cotizables | L39: BONO DE LA NACION ARGENTINA EN PESOS // A TASA VARIABLE 2017 (BONAC 2017) AY17 | N39: BACS BANCO DE CREDITO Y SECURITIZACION S.A. // CLASE VIII | P39: BPRO1 CUPON IMPAGO VTO. 29.01.02 | R39: AL PROYECTOS PRODUCT. E INFRAESTRUCTURA CLASE B
A40: BANCO CAJA DE AHORRO SOCIEDAD ANONIMA | C40: CHILE | E40: Fuente | H40: Dolar Bahameño | J40: CAPEX S.A. // ordinarias escriturales a (1 voto) u$s cable | L40: BONO DE LA NACION ARGENTINA EN PESOS // A TASA VARIABLE 2017 (BONAC 2017) AY17X | N40: BACS BANCO DE CREDITO Y SECURITIZACION S.A. // CLASE X | P40: PRE4 CUPON IMPAGO VTO. 01.02.02 | R40: AL RENTA BALANCEADA I CLASE A | T40: Percepcion
A41: BANCO CARLOS PELLEGRINI COOP.LTDO. | C41: CHINA REP.POPULAR | E41: FUENTE ARGENTINA | H41: Dolar caimano | J41: CAPEX S.A. // ordinarias escriturales a (1 voto) | L41: BONO DE LA NACION ARGENTINA EN PESOS // BADLAR PRIVADA + 200 PBS VTO 2017 AM17 | N41: BACS BANCO DE CREDITO Y SECURITIZACION S.A. // CLASE XI | P41: PRE3 CUPON IMPAGO VTO. 01.02.02 | R41: AL RENTA BALANCEADA I CLASE B | T41: 507 Dec 99/2019 – Art. 13 bis – inciso b) – Demás sujetos
A42: BANCO CASA COOP.LTDO. | C42: COLOMBIA | E42: FUENTE EXTRANJERA | H42: Dolar canadiense | J42: CAPUTO S.A. // ordinarias escriturales (1 voto) | L42: BONO DE LA NACION ARGENTINA EN PESOS // BADLAR PRIVADA + 200 PBS VTO 2017 AM17X | N42: BACS BANCO DE CREDITO Y SECURITIZACION S.A. // CLASE XV | P42: RC21 CUPON IMPAGO VTO.25.01.02 | R42: AL RENTA BALANCEADA II CLASE A | T42: 592 Ley 27.541 – Art. 35 – Inciso a) – Demás sujetos
A43: BANCO CAUDAL S.A. | C43: COLONIA DE GIBRALTAR | H43: Dolar de Barbados | J43: CARBOCLOR S. A. // ordinarias escriturales (1 voto) u$s cable | L43: BONO DE LA NACION ARGENTINA EN PESOS // BADLAR PRIVADA + 200 PBS VTO 2017 U$S CABLE | N43: BALANZ CAPITAL VALORES S.A. // CLASE 1 | P43: BCFD1 CUPON IMPAGO VTO. 01.03.02 | R43: AL RENTA BALANCEADA II CLASE B | T43: 594 Ley 27.541 – Art. 35 – Inciso b) – Demás sujetos
A44: BANCO CES COOPERATIVO LIMITADO | C44: COMORAS | E44: SI | H44: Dolar de Bélice | J44: CARBOCLOR S. A. // ordinarias escriturales (1 voto) | L44: BONO DE LA NACION ARGENTINA EN PESOS // BADLAR PRIVADA + 200 PTOS -VTO 2022 AA22 | N44: BALANZ CAPITAL VALORES S.A. // CLASE 2 | P44: BCDF1 CUPON IMPAGO VTO. 01.03.02 | R44: AL RENTA BALANCEADA II CLASE C | T44: 596 Ley 27.541 – Art. 35 – Inciso c) – Demás sujetos
A45: BANCO CETELEM ARGENTINA S.A. | C45: COMUNIDAD DE LAS BAHAMAS (Estado independiente) | E45: NO | H45: Dolar de Bermuda | J45: CARLOS CASADO S.A. // ordinarias escriturales (1 voto) | L45: BONO DE LA NACION ARGENTINA EN PESOS // BADLAR PRIVADA + 200 PTOS -VTO 2022 AA22X | N45: BALANZ CAPITAL VALORES S.A. // CLASE 2 DÓLAR U$S | P45: BCOR2 CUPON IMPAGO VTO. 01.03.02 | R45: AL RENTA DOLARES CLASE A | T45: 598 Ley 27.541 – Art. 35 – Inciso d) – Demás sujetos
A46: BANCO COFIDIS SA | C46: CONGO REP.POPULAR | H46: Dolar de Brunel | J46: CARLOS CASADO S.A. // ordinarias escriturales (5 votos) | L46: BONO DE LA NACION ARGENTINA EN PESOS // BADLAR PRIVADA + 200 PTOS -VTO 2022 DÓLAR U$S AA22D | N46: BALANZ CAPITAL VALORES S.A. // CLASE 3 | P46: BCOR1 CUPON IMPAGO VTO. 01.03.02 | R46: AL RENTA DOLARES CLASE B | T46: 600 Ley 27.541 – Art. 35 – Inciso e) – Demás sujetos
A47: BANCO COINAG COOP.LTDO.CAP.BERMUDEZ | C47: COREA DEMOCRATICA | E47: Tipo Inmueble | H47: Dolar de Hong Kong | J47: CELULOSA ARGENTINA S.A. // ordinarias escriturales (1 voto) | L47: BONO DE LA NACION ARGENTINA EN PESOS // BADLAR PRIVADA + 200 PTOS -VTO 2022 DÓLAR U$S AA22Y | N47: BALANZ CAPITAL VALORES S.A. // CLASE 4 | P47: BOHI 1 CUPON IMPAGO VTO.01.03.02 | R47: AL RENTA DOLARES CLASE C | T47: 531 PER GANAN Import. Def. Bs. para venta – Art. 40 1er párrafo
A48: BANCO COINAG S.A. | C48: COREA REPUBLICANA | E48: Casa | H48: Dolar de las Islas Salomon | J48: CELULOSA ARGENTINA S.A. // ordinarias escrituralles a (5 votos) | L48: BONO DE LA NACION ARGENTINA EN PESOS // BADLAR PRIVADA + 200 PTOS -VTO 2022 U$S CABLE AA22C | N48: BALANZ CAPITAL VALORES S.A. // CLASE 4 DÓLAR U$S | P48: BORD1 CUPON IMPAGO VTO. 01.03.02 | R48: AL RENTA FIJA CLASE A | T48: 080 PER GANAN Importación definitiva de bienes con C.V.D.I.
A49: BANCO COLUMBIA S.A. | C49: COSTA DE MARFIL | E49: Departamento | H49: Dolar de Sinapur | J49: CENTRAL PUERTO S.A. // ords escrit b (1 voto) - cotizables | L49: BONO DE LA NACION ARGENTINA EN PESOS // BADLAR PRIVADA + 200 PTOS -VTO 2022 U$S CABLE AA22Z | N49: BALANZ CAPITAL VALORES S.A. // CLASE 4 U$S CABLE | P49: BORN1 CUPON IMPAGO VTO. 01.03.02 | R49: AL RENTA FIJA CLASE B | T49: 081 PER GANAN Importación def. bienes para uso de imp con CVDI
A50: BANCO COMAFI S.A. | C50: COSTA RICA | E50: Departamento con cochera | H50: Dolar de Trinidad y Tobago | J50: CENTRAL URBANA S.A. // ordinarias escriturales (1 voto) | L50: BONO DE LA NACION ARGENTINA EN PESOS // BADLAR PRIVADA + 250 PBS VTO 2019 AMX9 | N50: BANCO DE SERVICIOS Y TRANSACCIONES S.A. // CLASE 7 | P50: PRO2 CUPON IMPAGO VTO. 01.03.02 | R50: AL RENTA FIJA CLASE C | T50: 082 PER GANAN Importación def. bienes para uso de imp sin CVDI
A51: BANCO COMERCIAL DE TANDIL S.A. | C51: CROACIA | E51: Cochera | H51: Dolar del caribe Oriental | J51: CERAMICA SAN LORENZO IND. Y COM.S.A. // ordinarias escriturales b (1 voto) | L51: BONO DE LA NACION ARGENTINA EN PESOS // BADLAR PRIVADA + 250 PBS VTO 2019 AMX9X | N51: BANCO DE SERVICIOS Y TRANSACCIONES S.A. // SUBORDINADAS CLASE 1 | P51: PRO1 CUPON IMPAGO VTO. 01.03.02 | R51: AL RENTA MIXTA CLASE A | T51: 083 PER GANAN Importación definitiva de bienes sin C.V.D.I.
A52: BANCO COMERCIAL DE TRES ARROYOS S.A. | C52: CUBA | E52: Local | H52: Dolar estadounidense | J52: CERAMICA SAN LORENZO IND. Y COM.S.A. // ordinarias escriturales b (1 voto) u$s cable | L52: BONO DE LA NACION ARGENTINA EN PESOS // BADLAR PRIVADA + 250 PBS VTO 2019 U$S CABLE | N52: BANCO CMF S.A. // CLASE 6 | P52: BPRO1 CUPON IMPAGO VTO. 01.03.02 | R52: AL RENTA MIXTA CLASE B | T52: 798 Servicios de transporte terrestre, aéreo o por vía acuática de pasajeros con destino fuera del país – Demás sujetos – Operaciones en efectivo
A53: BANCO COMERCIAL DEL NORTE | C53: DINAMARCA | E53: Lote de Terreno | H53: Dolar fijiano | J53: CIA. INDUSTRIAL CERVECERA S.A. // ordinarias escriturales a (5 votos) | L53: BONO DE LA NACION ARGENTINA EN PESOS // BADLAR PRIVADA + 275 PBS VTO 2018(BONAR 18B+275) AMX8X | N53: BANCO CMF S.A. // CLASE 7 | P53: PRE4 CUPON IMPAGO VTO. 01.03.02 | R53: AL RENTA MIXTA CLASE C | T53: 802 Servicios en el exterior contratados a través de agencias de viajes y turismo del país – Demás sujetos – Operaciones en efectivo
A54: BANCO COMERCIAL ISRAELITA S.A. | C54: DOMINICANA, REPUBLICA | E54: Country,quintas,etc. | H54: Dolar guyanés | J54: CIA. INDUSTRIAL CERVECERA S.A. // ordinarias escriturales b (1 voto) | L54: BONO DE LA NACION ARGENTINA EN PESOS // BADLAR PRIVADA + 275 PBS VTO 2018(BONAR 18B+275) DÓLAR U$S | N54: BANCO CMF S.A. // CLASE 8 | P54: PRE3 CUPON IMPAGO VTO. 01.03.02 | R54: AL RENTA MIXTA II CLASE A | T54: 818 Ventas de divisas para pagos al exterior
A55: BANCO COOP. DEL ESTE ARGENTINO LTDO.PARANA | C55: ECUADOR | E55: Mejoras Construcción | H55: Dolar jamaicano | J55: CIA. INTRODUCTORA DE BS.AS. S.A // ordinarias escriturales a (5 votos) | L55: BONO DE LA NACION ARGENTINA EN PESOS // BADLAR PRIVADA + 275 PBS VTO 2018(BONAR 18B+275) DÓLAR U$S AMX8 | N55: BANCO CMF S.A. // CLASE 9 | P55: PRO3 CUPON IMPAGO VTO. 28.02.02 | R55: AL RENTA MIXTA II CLASE B
A56: BANCO COOPERATIVO DE CASEROS LTD. | C56: EGIPTO | E56: Rurales con vivienda | H56: Dolar liberiano | J56: CIA. INTRODUCTORA DE BS.AS. S.A // ordinarias escriturales b (1 voto) | L56: BONO DE LA NACION ARGENTINA EN PESOS // BADLAR PRIVADA + 275 PBS VTO 2018(BONAR 18B+275) U$S CABLE | N56: BANCO COMAFI S.A. // CLASE 18 | P56: PRO4 CUPON IMPAGO VTO. 28.02.02 | R56: AL RENTA MIXTA II CLASE C | T56: Tipo de operación - Reten y Perc
A57: BANCO COOPERATIVO DE LA PLATA LTDO. | C57: EL COMMONWEALTH DE DOMINICA (Estado Asociado) | E57: Rurales sin vivienda | H57: Dolar namibio | J57: CIA.TRANSP.E.E. ALTA TENSION TRANSENER S.A. // ordinarias escriturales b (1 voto) u$s cable | L57: BONO DE LA NACION ARGENTINA EN PESOS // BADLAR PRIVADA + 300 PBS VTO 2017 AO17 | N57: BANCO COMAFI S.A. // CLASE 9 | P57: RC21 CUPON IMPAGO VTO.28.02.02 | R57: AL RENTA VARIABLE CLASE A | T57: Retención
A58: BANCO COOPERATIVO NICOLAS LEVALLE LTDO. | C58: EL SALVADOR | E58: Otros Inmuebles | H58: Dolar neozelandes | J58: CIA.TRANSP.E.E. ALTA TENSION TRANSENER S.A. // ordinarias escriturales b (1 voto) | L58: BONO DE LA NACION ARGENTINA EN PESOS // BADLAR PRIVADA + 300 PBS. VTO. 2017 AO17X | N58: BANCO DE GALICIA Y BS.AS. S.A. // CLASE III BYC3O | P58: BX92 CUPON IMPAGO VTO. 15.03.02 | R58: AL RENTA VARIABLE CLASE B | T58: Percepción
A59: BANCO COOPESUR COOP.LTDO. | C59: EMIRATOS ARABES UNIDOS (Estado independiente) | H59: Dolar taiwanes | J59: COLORIN IND. DE MAT.SINT. S.A. // ordinarias escriturales (1 voto) | L59: BONO DE LA NACION ARGENTINA EN PESOS // BADLAR PRIVADA + 300 PBS. VTO. 2017 U$S CABLE | N59: BANCO DE GALICIA Y BS.AS. S.A. // CLASE III BYC3X | P59: BCOR1 CUPON IMPAGO VTO. 01.11.01 | R59: ALIANZA DE CAPITALES
A60: BANCO COSCREA COOP.LTDO. | C60: ERITREA | E60: Destino Inmueble | H60: Dolar zimbabuense | J60: CONSULTATIO S.A. // ordinarias escriturales (1 voto) | L60: BONO DE LA NACION ARGENTINA EN PESOS // BADLAR PRIVADA + 325 PBS VTO 2020(BONAR 20B+325) AM20 | N60: BANCO DE GALICIA Y BS.AS. S.A. // CLASE IV | P60: BCOR1 CUPON IMPAGO VTO. 01.12.01 | R60: ALLARIA DOLARES PLUS CLASE A | T60: Retencion
A61: BANCO CREDICOOP COOPERATIVO LIMITADO | C61: ESLOVACA, REPUBLICA | E61: Alquiler | H61: Dong vietnamita | J61: CONTINENTAL URBANA SOCIEDAD ANONIMA INVERSORA // ordinarias escriturales 1 voto dólar (u$s) | L61: BONO DE LA NACION ARGENTINA EN PESOS // BADLAR PRIVADA + 325 PBS VTO 2020(BONAR 20B+325) AM20X | N61: BANCO DE GALICIA Y BS.AS. S.A. // O.N. CLASE 1 | P61: CUPON 4 LETRA EN EURO VTO. 28.5.16 | R61: ALLARIA DOLARES PLUS CLASE B | T61: 019 RET GANAN INTERESES OPERAC. REALIZADAS EN ENTIDADES FINANCIERAS
A62: BANCO CREDITO DE CUYO S.A. | C62: ESLOVENIA | E62: Afectado a la explotación | H62: DRACHMA griega | J62: CONTINENTAL URBANA SOCIEDAD ANONIMA INVERSORA // ordinarias escriturales 1 voto u$s cable | L62: BONO DE LA NACION ARGENTINA EN PESOS // BADLAR PRIVADA + 325 PBS VTO 2020(BONAR 20B+325) DÓLAR U$S AM20D | N62: BANCO DE GALICIA Y BS.AS. S.A. // SUBORDINADAS CLASE II | P62: CUPON 5 L.EN EURO VTO. 28.5.2021 | R62: ALLARIA ESTRATEGICO CLASE A | T62: 021 RET GANANCIAS INTERESES POR OTRO TIPO DE OPERACIONES
A63: BANCO CREDITO PROVINCIAL S.A. | C63: ESPAÑA | E63: Inversión | H63: Dram Armenio | J63: CONTINENTAL URBANA SOCIEDAD ANONIMA INVERSORA // ordinarias escriturales 1 voto | L63: BONO DE LA NACION ARGENTINA EN PESOS // BADLAR PRIVADA + 325 PBS VTO 2020(BONAR 20B+325) DÓLAR U$S AM20Y | N63: BANCO DE GALICIA Y BS.AS. S.A. // SUBORDINADAS CLASE II DÓLAR U$S | P63: CUPON FIJO LETRA EXTERNA VTO.28.5.26 | R63: ALLARIA ESTRATEGICO CLASE B | T63: 022 COMPRA VENTA DE GRANOS Y LEGUMBRES SECAS - ART. 10 INC. A) APARTADO 2 - OPERACIONES PRIMARIAS
A64: BANCO DE BALCARCE COOPERATIVO LIMITADO | C64: ESTADO ASOCIADO DE GRANADA (Estado independiente) | E64: Recreo o Veraneo | H64: ECU | J64: CRESUD S.A.C.I.F. y A. // ordinarias escriturales (1 voto) u$s cable | L64: BONO DE LA NACION ARGENTINA EN PESOS // BADLAR PRIVADA + 325 PBS VTO 2020(BONAR 20B+325) U$S CABLE AM20C | N64: BANCO DE GALICIA Y BS.AS. S.A. // SUBORDINADAS CLASE II U$S CABLE | P64: CUPON IMPAGO VEY4 S.74 VTO.11.07.03 | R64: ALLARIA RENTA DÓLAR LEY 27260 CLASE A | T64: 023 COMPRA VENTA DE GRANOS Y LEGUMBRES SECAS ART. 10 INC. B)
A65: BANCO DE BERISSO COOP.LTDO. | C65: ESTADO DE BAHREIN (Estado independiente) | E65: Otros | H65: Escudo caboverdiano | J65: CRESUD S.A.C.I.F. y A. // ordinarias escriturales (1 voto) dólar (u$s) | L65: BONO DE LA NACION ARGENTINA EN PESOS // BADLAR PRIVADA + 325 PBS VTO 2020(BONAR 20B+325) U$S CABLE AM20Z | N65: BANCO DE INVERSIÓN Y COMERCIO EXTERIOR S.A. // CLASE 2 | P65: CUPON IMPAGO VEY4 VTO.11.08.03 | R65: ALLARIA RENTA DÓLAR LEY 27260 CLASE B | T65: 024 COMPRA VENTA DE GRANOS Y LEGUMBRES SECAS ART. 10 INC. C)
A66: BANCO DE CASEROS S.A. | C66: ESTADO DE KUWAIT (Estado independiente) | H66: Escudo de Timor | J66: CRESUD S.A.C.I.F. y A. // ordinarias escriturales (1 voto) | L66: BONO DE LA NACION ARGENTINA VINCULADO AL DÓLAR // 0,75%VTO. JUNIO 2017 AJ17 | N66: BANCO DE INVERSIÓN Y COMERCIO EXTERIOR S.A. // CLASE 4 | P66: CUPON AMORT. VEY4 VTO.11.05.04 | R66: ALLARIA RENTA DÓLAR LEY 27260 CLASE C | T66: 025 RET GAN COMISIONES RETRIBUCIONES DERIVADAS DE ACTIVIDAD DE COMISIONISTAS, REMATADORES Y CONSIGNATARIOS
A67: BANCO DE CATAMARCA | C67: ESTADO DE QATAR (Estado independiente) | E67: PROVINCIAS | H67: Escudo portuges | J67: DISTRIBUIDORA DE GAS CUYANA S.A. // ords escrit b (1 voto) - cotizables u$s cable | L67: BONO DE LA NACION ARGENTINA VINCULADO AL DÓLAR // 0,75%VTO. JUNIO 2017 AJ17X | N67: BANCO DE SERVICIOS FINANCIEROS S.A. // CLASE 15 | P67: CUPON IMPAGO VEY4 S.74 VTO.11.05.02 | R67: ALLARIA SINCERAM.FISCAL LEY 27260 CLASE B | T67: 026 COMPRA VENTA DE GRANOS Y LEGUMBRES SECAS - ART. 10 INC. D) APARTADO 2 - COMISIONES
A68: BANCO DE COMERCIO | C68: ESTADO LIBRE ASOCIADO DE PUERTO RICO (Estado asoc. a EEUU) | E68: Buenos Aires | H68: EURO | J68: DISTRIBUIDORA DE GAS CUYANA S.A. // ords escrit b (1 voto) - cotizables | L68: BONO DE LA NACION ARGENTINA VINCULADO AL DÓLAR // 0,75%VTO. JUNIO 2017 DÓLAR U$S | N68: BANCO DE SERVICIOS FINANCIEROS S.A. // CLASE 16 | P68: CUPON IMPAGO VBY4 T.7 S.75 VTO.11.5.03 | R68: ALLARIA SINCERAM.FISCAL LEY 27260 CLASE C | T68: 028 COMPRA VENTA DE GRANOS Y LEGUMBRES SECAS - ART. 10 INC. A) APARTADO 2 - OPERACIONES SECUNDARIAS Y OTRAS
A69: BANCO DE CORONEL DORREGO Y T.LAUQUEN | C69: ESTADOS UNIDOS | E69: Catamarca | H69: Florín arubeño | J69: DOMEC CIA. ARTEF.DOMEST.S.A.I.C. y F. // ords nominativas no endosables (1 voto) | L69: BONO DE LA NACION ARGENTINA VINCULADO AL DÓLAR // 0,75%VTO. JUNIO 2017 U$S CABLE | N69: BANCO DE SERVICIOS FINANCIEROS S.A. // CLASE 17 | P69: CUPON AMORT. VBY4 T.7 S.75 VTO.11.5.03 | R69: ALPHA ACCIONES CLASE A | T69: 030 ALQUILERES O ARRENDAMIENTOS DE BIENES MUEBLES
A70: BANCO DE CORONEL PRINGLES S.A. | C70: ESTONIA | E70: Chaco | H70: Florín de las Antillas Holandesas | J70: DYCASA S.A. // ordinarias escriturales b (1 voto) | L70: BONO DE LA NACION ARGENTINA VINCULADO AL DÓLAR // 0,75%VTO. SEPT 2017(BONAD 0,75%SEPT2017) AS17 | N70: BANCO DE SERVICIOS FINANCIEROS S.A. // CLASE 18 | P70: CUPON IMPAGO VBY4 S.75 T.7 V.11.06.03 | R70: ALPHA ACCIONES CLASE B | T70: 031 BIENES INMUEBLES URBANOS, INCLUIDOS LOS EFECTUADOS BAJO MODALIDAD DE LEASING - INCLUYE SUBURBANOS
A71: BANCO DE CORRIENTES S.A. | C71: ETIOPIA | E71: Chubut | H71: Florin de Surinam | J71: ELECTROMAC S.A.I. y C. // ordinarias nominativas no endosables (1 voto) | L71: BONO DE LA NACION ARGENTINA VINCULADO AL DÓLAR // 0,75%VTO. SEPT 2017(BONAD 0,75%SEPT2017) AS17X | N71: BANCO DE SERVICIOS FINANCIEROS S.A. // CLASE 19 | P71: CUPON IMPAGO VEY4 S.74 VTO.11.06.03 | R71: ALPHA ACCIONES CLASE C | T71: 032 BIENES INMUEBLES RURALES, INCLUIDOS LOS EFECTUADOS BAJO MODALIDAD DE LEASING - INCLUYE SUBRURALES
A72: BANCO DE CREDITO ARGENTINO S.A. | C72: FEDERACION DE SAN CRISTOBAL (Islas Saint Kitts and Nevis) | E72: Ciudad Autónoma de Buenos Aires | H72: Florin holandes | J72: EMPRESA DISTRIB. Y COMERCIALIZADORA NORTE S.A. (EDENOR S.A.) // ordinarias escriturales b (1 voto) u$s cable | L72: BONO DE LA NACION ARGENTINA VINCULADO AL DÓLAR // 0,75%VTO. SEPT 2017(BONAD 0,75%SEPT2017) DÓLAR U$S | N72: BANCO HIPOTECARIO S.A. // CLASE XL BH40O | P72: CUPON IMPAGO VEY4 VTO.11.08.03 | R72: ALPHA ACCIONES CLASE D | T72: 035 RET GANANCIAS - REGALIAS
A73: BANCO DE CREDITO COMERCIAL | C73: FIJI, ISLAS | E73: Córdoba | H73: Forint hungaro | J73: EMPRESA DISTRIB. Y COMERCIALIZADORA NORTE S.A. (EDENOR S.A.) // ordinarias escriturales b (1 voto) | L73: BONO DE LA NACION ARGENTINA VINCULADO AL DÓLAR // 0,75%VTO.2017(BONAD 0,75%2017) AF17X | N73: BANCO HIPOTECARIO S.A. // CLASE XL BH40X | P73: CUPON AMORT.VEY4 VTO.11.08.03 | R73: ALPHA ACCIONES CLASE E | T73: 040 RET GANAN INTERESES DE DEUDAS, INCLUIDAS OBLIGACIONES NEGOCIABLES - ART. 81 INC. A)
A74: BANCO DE CREDITO RURAL ARGENTINO S.A. | C74: FILIPINAS | E74: Corrientes | H74: Franco belga | J74: EMPRESA DISTRIBUIDORA ELECTRICA REGIONAL S.A. - EMDERSA // escriturales (1 voto) | L74: BONO DE LA NACION ARGENTINA VINCULADO AL DÓLAR // 0,75%VTO.2017(BONAD 0,75%2017) AF17 | N74: BANCO HIPOTECARIO S.A. // CLASE XLI | P74: CUPON IMPAGO VEY4 S.74 VTO.11.10.03 | R74: ALPHA ACCIONES CLASE I | T74: 043 RET GANAN INTERESES ACCIONARIOS, EXCEDENTES Y RETORNOS DISTRIBUIDOS ENTRE ASOCIADOS
A75: BANCO DE ENTRE RIOS S.A. | C75: FINLANDIA | E75: Entre Rios | H75: Franco burundés | J75: ENDESA COSTANERA S. A. // ordinarias ecriturales de 1 voto u$s cable | L75: BONO DE LA NACION ARGENTINA VINCULADO AL DÓLAR // 0,75%VTO.2017(BONAD 0,75%2017) U$S CABLE | N75: BANCO HIPOTECARIO S.A. // CLASE XLII | P75: CUPON IMPAGO VEY4 VTO. 11.11.03 | R75: ALPHA AHORRO CLASE A | T75: 051 RET GANAN OBLIGACIONES DE HACER O POR NO EJERCER UNA ACTIVIDAD
A76: BANCO DE FORMOSA S.A. | C76: FRANCIA | E76: Formosa | H76: Franco CFA | J76: ENDESA COSTANERA S. A. // ordinarias ecriturales de 1 voto | L76: BONO DE LA NACION ARGENTINA VINCULADO AL DÓLAR // 0,75%VTO.2017(BONAD 0,75%2017)DÓLAR U$S | N76: BANCO HIPOTECARIO S.A. // CLASE XLIII | P76: CUPON AMORT.VEY4 VTO.11.11.03 | R76: ALPHA AHORRO CLASE B | T76: 053 RET GAN OPERACIONES REALIZADAS A TRAVES DE MERCADOS DE CEREALES A TERMINO
A77: BANCO DE GALICIA Y BUENOS AIRES S.A. | C77: GABON | E77: Jujuy | H77: Franco CFA | J77: EUROMAYOR S.A. DE INVERSIONES // ordinarias escriturales b (1 voto) | L77: BONO DE LA NACION ARGENTINA VINCULADO AL DÓLAR // 2,40%VTO 2018(BONAD 2,40% 2018) AM18 | N77: BANCO HIPOTECARIO S.A. // CLASE XLVI | P77: CUPON IMPAGO VEY4 VTO.11.12.03 | R77: ALPHA AHORRO CLASE C | T77: 055 RET GAN DISTRIBUCION DE PELICULAS CINEMATOGRAFICAS Y TRANSMISION DE PROGRAMAS DE TELEVISION VIA SATELITAL
A78: BANCO DE INVERSION Y COMERCIO EXTERIOR S.A. | C78: GAMBIA | E78: La Pampa | H78: Franco CFP | J78: FERRUM S.A. DE CERAMICA Y METALURGIA // ordinarias escriturales a (5 votos) | L78: BONO DE LA NACION ARGENTINA VINCULADO AL DÓLAR // 2,40%VTO 2018(BONAD 2,40% 2018) AM18X | N78: BANCO HIPOTECARIO S.A. // CLASE XXIX | P78: CUPON IMPAGO VEY4 VTO.12.01.04 | R78: ALPHA MEGA CLASE A | T78: 056 RETENCION - GANANCIAS - ACTORES
... A90: BANCO DE LA PROVINCIA DE JUJUY | C90: HAITI | E90: Tierra del Fuego | H90: Guarani paraguayo | J90: GRIMOLDI S.A. // ordinarias escriturales a (5 votos) | L90: BONOS AL 10% PCIA. DE BUENOS AIRES // con vto. el 5 de julio de 2004 - serie n° 10 | N90: BANCO ITAÚ ARGENTINA S.A. // CLASE 17 | P90: Carga manual | R90: ALPHA PESOS CLASE B | T90: 116 RET GAN PROFESIONES LIBERALES, SINDICO, DIRECTOR DE S.A., ETC.
A91: BANCO DE LA PROVINCIA DE LA RIOJA | C91: HONDURAS | E91: Tucumán | H91: Hryvnia ucraniana | J91: GRIMOLDI S.A. // ordinarias escriturales b (1 voto) | L91: BONOS AL 10,75% PCIA. DE BUENOS AIRES // CON VENCIMIENTO 2005 CEDEL | N91: BANCO ITAÚ ARGENTINA S.A. // CLASE 18 | R91: ALPHA PESOS PLUS CLASE A | T91: 117 IMPUESTO A LAS GANANCIAS - REGIMEN DE RETENCION 2% FUTBOLISTAS
A92: BANCO DE LA PROVINCIA DE MISIONES | C92: HONK KONG (Territorio de China) | H92: Kina de Papua Nueva Guinea | J92: GRUPO CLARIN S.A. // ordinarias clase b (1 voto) u$s cable | L92: BONOS AL 10,75% PCIA. DE BUENOS AIRES // CON VENCIMIENTO 2005 EUROCLEAR | N92: BANCO ITAÚ ARGENTINA S.A. // CLASE 19 | R92: ALPHA PESOS PLUS CLASE B | T92: 118 IMPUESTO A LAS GANANCIAS - REGIMEN DE RETENCION 28% FUTBOLISTAS
A93: BANCO DE LA PROVINCIA DE RIO NEGRO | C93: HUNGRIA | E93: OTROS EGRESOS | H93: Kip lao | J93: GRUPO CLARIN S.A. // ordinarias clase b (1 voto) | L93: BONOS AL 12,5% PCIA. DE BUENOS AIRES // vto. el 15 de marzo de 2002 - serie 2 u$s cable | N93: BANCO MACRO S.A. // CLASE 2 OROY2 | R93: ALPHA PLANEAMIENTO CONSERVADOR CLASE A | T93: 119 RET GAN PROFESIONES LIBERALES Y OFICIOS
A94: BANCO DE LA PROVINCIA DE SAN LUIS | C94: INDETERMINADO (AFRICA) | E94: Servicios Públicos - Energía Electrica | H94: Koruna checo | J94: GRUPO CONCESIONARIO DEL OESTE S.A. // ordinarias escriturales b (1 voto) | L94: BONOS AL 12,50% PCIA. DE BUENOS AIRES // vto el 15 de marzo de 2002 - serie n° 2 | N94: BANCO MACRO S.A. // CLASE 2 OROY5 | R94: ALPHA PLANEAMIENTO CONSERVADOR CLASE B | T94: 124 RET GANANCIAS CORREDORES, VIAJANTES Y DESPACHANTES DE ADUANA
A95: BANCO DE LA PROVINCIA DE STGO.DEL ESTERO | C95: INDETERMINADO (AMERICA) | E95: Servicios Públicos - Gas | H95: Krona islandesa | J95: GRUPO FINANCIERO GALICIA S.A. // ordinarias escriturales b (1 voto) dólar (u$s) | L95: BONOS AL 12,75% PCIA. DE BUENOS AIRES // vto el 1 de agosto de 2003 - serie 13 | N95: BANCO MACRO S.A. // CLASE 2 U$S CABLE | R95: ALPHA PLANEAMIENTO CONSERVADOR CLASE C | T95: 160 RENTAS DEL TRABAJO PERSONAL BAJO RELACION DE DEPENDENCIA Y OTROS
A96: BANCO DE LA PROVINCIA DEL CHACO | C96: INDETERMINADO (ASIA) | E96: Servicios Públicos - Agua | H96: Kuna croata | J96: GRUPO FINANCIERO GALICIA S.A. // ordinarias escriturales b (1 voto) u$s cable | L96: BONOS AL 13,25% PCIA. DE BUENOS AIRES // vto el 29 de marzo de 2010 - serie 7 u$s cable | N96: BANCO MACRO S.A. // CLASE B | R96: ALPHA PLANEAMIENTO CONSERVADOR CLASE D | T96: 191 RET GAN TRANSFERENCIA DE INMUEBLES - OPERACIONES GRAVADAS EN GANANCIAS
A97: BANCO DE LA REP. ORIENTAL DEL URUGUAY | C97: INDETERMINADO (EUROPA) | E97: Servicios Públicos - Telefonía | H97: Kwacha malawiano | J97: GRUPO FINANCIERO GALICIA S.A. // ordinarias escriturales b (1 voto) | L97: BONOS AL 13,25% PCIA. DE BUENOS AIRES // vto el 29 de marzo de 2010 - serie n° 7 | N97: BANCO MACRO S.A. // SUBORDINADAS CLASE A | R97: ALPHA PLANEAMIENTO CONSERVADOR CLASE I | T97: 192 RET GAN TRANSFERENCIA DE INMUEBLES - OPERACIONES CON GANANCIA REDUCIDA AL 50%
A98: BANCO DE LA RIBERA COOP.LTDO. SAN NICOLAS | C98: INDETERMINADO (OCEANIA) | E98: Seguros | H98: Kwacha zambiano | J98: HULYTEGO S.A.I.C. // ordinarias nominativas no endosables (1 voto) | L98: BONOS AL 13,25% PCIA. DE BUENOS AIRES // vto el 29 de marzo de 2010 - serie n° 7 c.ext. | N98: BANCO MACRO S.A. // SUBORDINADAS CLASE A DÓLAR U$S | R98: ALPHA PLANEAMIENTO DINAMICO CLASE A | T98: 193 RET GAN TRANSFERENCIA DE INMUEBLES - BENEFICIARIOS DEL EXTERIOR
A99: BANCO DE LABOULAYE COOP.LTDO.CORDOBA | C99: INDIA | E99: Gastos de Combustible | H99: Kwanza angoleño | J99: INSTITUTO ROSENBUSCH S.A. DE BIOLOGIA E. y A. // ords nominativas no endosables a (5 votos) | L99: BONOS AL 13,75% PCIA. DE BUENOS AIRES // VTO EL 5 DE SETIEMBRE DE 2007 - SERIE 14 | N99: BANCO PATAGONIA S.A. // CLASE III | R99: ALPHA PLANEAMIENTO DINAMICO CLASE B | T99: 196 RET GAN TRANSFERENCIA DE CUOTAS Y PARTICIPACIONES SOCIALES RG 3026
A100: BANCO DE LAS COMUNIDADES COOP.LTDO. | C100: INDONESIA | E100: Propaganda, Publicidad y Merchandising | H100: Kyat myanmaro | J100: INSTITUTO ROSENBUSCH S.A. DE BIOLOGIA E. y A. // ords nominativas no endosables b (1 voto) | L100: BONOS CHAQUEÑOS DE CONSOLIDACION II LEY 4385 EN DOL.ESTADOUN. // 1RA SERIE | N100: BANCO SAENZ S.A. // SERIE IX | R100: ALPHA PLANEAMIENTO DINAMICO CLASE C | T100: 200 RET GAN COMPRAVENTA DE ACCIONES POR PERSONAS FISICAS Y SUCESIONES INDIVISAS RESIDENTES EN EL PAIS
A101: BANCO DE LOS ARROYOS COOP.LTDO. | C101: IRAK | E101: Viáticos, refrigerio y transporte | H101: Lari georgiano | J101: INSUMOS AGROQUIMICOS S.A. // ordinarias escriturales b (1 voto) | L101: BONOS CHAQUEÑOS DE CONSOLIDACION II LEY 4385 EN DOL.ESTADOUN. // 1RA SERIE DÓLAR (U$S) | N101: BANCO SAENZ S.A. // SERIE VIII | R101: ALPHA PLANEAMIENTO DINAMICO CLASE D | T101: 235 RET GAN NOMINATIVIDAD DE TITULOS VALORES - SALDOS IMPAGOS
A102: BANCO DE MENDOZA S.A. | C102: IRAN | E102: Gastos médicos y análisis preocupacionales | H102: Lat leton | J102: INTA IND. TEXTIL ARG. S.A. // ordinarias escriturales a (3 votos) | L102: BONOS CHAQUEÑOS DE CONSOLIDACION II LEY 4385 EN DOL.ESTADOUN. // 2DA SERIE | N102: BANCO SANTANDER RÍO S.A. // CLASE IX | R102: ALPHA PLANEAMIENTO DINAMICO CLASE I | T102: 237 MUTUOS HIPOTECARIOS
A103: BANCO DE MISIONES S.A. | C103: IRLANDA (EIRE) | E103: Sistemas de seguridad y transporte de caudales | H103: Lek albano | J103: INTA IND. TEXTIL ARG. S.A. // ordinarias escriturales b (1 voto) | L103: BONOS CHAQUEÑOS DE CONSOLIDACION II LEY 4385 EN DOL.ESTADOUN. // 2DA SERIE DÓLAR (U$S) | N103: BANCO SANTANDER RÍO S.A. // CLASE VII | R103: ALPHA PLANEAMIENTO EQUILIBRADO CLASE A | T103: 240 RET GAN NOMINATIVIDAD DE TITULOS VALORES - SALDOS PAGOS
A104: BANCO DE OLAVARRIA S.A. | C104: ISLA CHRISTMAS | E104: Alquiler de inmuebles, maquinarias y equipos (incluye Leasing) | H104: Lempira hondureño | J104: INVERSORA JURAMENTO S.A. // ordinarias escrit. clase b (1 voto) | L104: BONOS CHAQUEÑOS DE CONSOLIDACION II LEY 4385 EN DOL.ESTADOUN. // 2DA SERIE U$S CABLE | N104: BANCO SANTANDER RÍO S.A. // CLASE VIII | R104: ALPHA PLANEAMIENTO EQUILIBRADO CLASE B | T104: 428 COMPRA VENTA DE GRANOS Y LEGUMBRES SECAS - ART. 10 INC. A) APARTADO 3 - OPERACIONES PRIMARIAS
A105: BANCO DE PARANA | C105: ISLA DE COCOS O KEELING | E105: Otros | H105: Leone de Sierra Leona | J105: IRSA INVERSIONES Y REPRESENTACIONES S.A. // ordinarias escriturales (1 voto) u$s cable | L105: BONOS CHAQUEÑOS DE CONSOLIDACION II LEY 4385 EN DOL.ESTADOUN. // 3RA SERIE | N105: BANCO SANTANDER RÍO S.A. // CLASE XI | R105: ALPHA PLANEAMIENTO EQUILIBRADO CLASE C | T105: 429 COMPRA VENTA DE GRANOS Y LEGUMBRES SECAS - ART. 10 INC. D) APARTADO 3 - COMISIONES
A106: BANCO DE PREVISION SOCIAL S.A. | C106: ISLA DE MAN (Territorio del Reino Unido) | H106: Leu de Rumania | J106: IRSA INVERSIONES Y REPRESENTACIONES S.A. // ordinarias escriturales (1 voto) | L106: BONOS CHAQUEÑOS DE CONSOLIDACION II LEY 4385 EN DOL.ESTADOUN. // 3RA SERIE DÓLAR (U$S) | N106: BANCO SANTANDER RÍO S.A. // CLASE XII | R106: ALPHA PLANEAMIENTO EQUILIBRADO CLASE D | T106: 430 COMPRA VENTA DE GRANOS Y LEGUMBRES SECAS - ART. 10 INC. A) APARTADO 3 - OPERACIONES SECUNDARIAS Y OTRAS
A107: BANCO DE RIO TERCERO COOP.LTDO. | C107: ISLA DE NORFOLK | E107: Quebranto | H107: Leu moldavo | J107: JUAN MINETTI S.A. // ordinarias escriturales (1 voto) u$s cable | L107: BONOS CHAQUEÑOS DE CONSOLIDACION II LEY 4385 EN DOL.ESTADOUN. // 3RA SERIE U$S CABLE | N107: BANCO SANTANDER RÍO S.A. // CLASE XIII | R107: ALPHA PLANEAMIENTO EQUILIBRADO CLASE I | T107: 446 PROVEEDORES DE EMPRESAS MINERAS INSCRIPTOS EN EL REGISTRO
A108: BANCO DE SALTA S.A. | C108: ISLA DE SAN PEDRO Y MIGUELON | E108: Act. No Promovida | H108: LEV | J108: JUAN MINETTI S.A. // ordinarias escriturales (1 voto) | L108: BONOS DE AMORTIZACION - PROVINCIA DE MENDOZA // AL 5,5% CON VENCIMIENTO EN 2018 DÓLAR U$S | N108: BANCO SANTANDER RÍO S.A. // CLASE XIV | R108: ALPHA RECURSOS NATURALES CLASE A | T108: 447 PROVEEDORES DE EMPRESAS MINERAS NO INSCRIPTOS EN EL REGISTRO - ENAJENACION DE BIENES Y/O PRESTACION DE SERVICIOS Y/O LOCACION DE BIENES MUEBLES Y/O INMUEBLES
A109: BANCO DE SAN JUAN S.A. | C109: ISLA QESHM | E109: Act. Promovida | H109: Lev b=FAlgaro | J109: LEDESMA S.A.A.I. // ords nomin no endosables (1 voto) u$s cable | L109: BONOS DE AMORTIZACION - PROVINCIA DE MENDOZA // AL 5,5% CON VENCIMIENTO EN 2018 EUROCLEAR BARX1 | N109: BANCO SANTANDER RÍO S.A. // CLASE XV | R109: ALPHA RECURSOS NATURALES CLASE B | T109: 448 PROVEEDORES DE EMPRESAS MINERAS NO INSCRIPTOS EN EL REGISTRO - RESTO DE OPERACIONES
A110: BANCO DE SANTA CRUZ S.A. | C110: ISLANDIA | H110: Libra chipriota | J110: LEDESMA S.A.A.I. // ords nominativas no endosables (1 voto) | L110: BONOS DE AMORTIZACION - PROVINCIA DE MENDOZA // AL 5,5% CON VENCIMIENTO EN 2018 EUROCLEAR BARY1 | N110: BANCO SANTANDER RÍO S.A. // CLASE XVI | R110: ALPHA RECURSOS NATURALES CLASE C | T110: 449 PROVEEDORES - SUJETOS NO INSCRIPTOS EN EL IMPUESTO A LAS GANANCIAS
A111: BANCO DE SANTA FE SOCIEDAD ANONIMA | C111: ISLAS AZORES | H111: Libra de Gibraltar | J111: LEYDEN S.A.I.C. y F. // ordinarias nominativas no endosables b (1 voto) | L111: BONOS DE AMORTIZACION - PROVINCIA DE MENDOZA // AL 5,5% CON VENCIMIENTO EN 2018 U$S CABLE BARXC | N111: BANCO SANTANDER RÍO S.A. // CLASE XVII | R111: ALPHA RECURSOS NATURALES CLASE D | T111: 500 PROVEEDORES - SUJETOS ADHERIDOS AL REGIMEN SIMPLIFICADO (RS) EXCEDIDOS DEL MONTO MAXIMO
A112: BANCO DE SANTIAGO DEL ESTERO S.A. | C112: ISLAS CAIMAN (Territorio no autónomo del Reino Unido) | H112: Libra de Santa Helena | J112: LONGVIE S.A. // ordinarias escriturales a (5 votos) | L112: BONOS DE AMORTIZACION - PROVINCIA DE MENDOZA // AL 5,5% CON VENCIMIENTO EN 2018 U$S CABLE C.EXT. EUROCLEAR BARYC | N112: BANCO SUPERVIELLE S.A. // CLASE A | R112: ALPHA RECURSOS NATURALES CLASE I | T112: 526 RIGI - OTRAS GANANCIAS NO PREVISTAS - ART. 185 TERCER PARRAFO LEY 27.742
...

Sheet PASIVO
G1: PASIVO
J2: Control
B3: TOTAL PASIVO s/detalle | G3: =+F5+F7 -> 0 | J3: =+G3-G9-G64-G119-G146-G173-G175-G177-G179-G181 -> 0
D5: Total del Pasivo corriente | F5: 0
D7: Total del pasivo no corriente | F7: 0
C9: 2,1- Deudas comerciales | G9: =+G11+G37 -> 0
D11: 2,1,1- Deudas comerciales locales | G11: =+G35 -> 0
E13: Nombre y Apellido, Denominación o Razón Social | F13: N° C.U.I.T. | G13: SALDO AL CIERRE
D14: 1
D15: 2
D16: 3
D17: 4
D18: 5
D19: 6
D20: 7
D21: 8
D22: 9
D23: 10
D24: 11
D25: 12
... D34: 21
D35: TOTAL DEUDAS COMERCIALES DEL PAIS | G35: =SUM(G14:G34) -> 0
D37: 2,1,2- Deudas comerciales exterior | G37: =+G61 -> 0
D39: # | E39: Nombre y Apellido, Denominación o Razón Social | F39: N° C.U.I.T. | G39: SALDO AL CIERRE
D40: 1
D41: 2
D42: 3
D43: 4
D44: 5
D45: 6
D46: 7
D47: 8
D48: 9
D49: 10
D50: 11
D51: 12
... D60: 21
D61: TOTAL DEUDAS COMERCIALES DEL EXTERIOR | G61: =SUM(G40:G60) -> 0
C64: 2,2- Deudas Bancarias y Financieras | G64: =+G66+G92 -> 0
D66: 2,2,1- Deudas bancarias y financieras locales | G66: =+G90 -> 0 | Q66: =0.5/100 -> 0.005
D68: # | E68: Nombre y Apellido, Denominación o Razón Social | F68: N° C.U.I.T. | G68: SALDO AL CIERRE
D69: 1
D70: 2
D71: 3
D72: 4
D73: 5
D74: 6
D75: 7
D76: 8
D77: 9
D78: 10
D79: 11
D80: 12
... D89: 21
D90: TOTAL DEUDAS COMERCIALES DEL PAIS | G90: =SUM(G69:G89) -> 0
D92: 2,2,2- Deudas bancarias y financieras exterior | G92: =+G116 -> 0
E94: Nombre y Apellido, Denominación o Razón Social | F94: PAIS / CUIT | G94: SALDO AL CIERRE
D95: 1
D96: =+D95+1 -> 2
D97: =+D96+1 -> 3
D98: =+D97+1 -> 4
D99: =+D98+1 -> 5
D100: =+D99+1 -> 6
D101: =+D100+1 -> 7
D102: =+D101+1 -> 8
D103: =+D102+1 -> 9
D104: =+D103+1 -> 10
D105: =+D104+1 -> 11
D106: =+D105+1 -> 12
D107: =+D106+1 -> 13
... D115: =+D114+1 -> 21
D116: TOTAL DEUDAS BANCARIAS Y FINANCIERAS DEL EXTERIOR | G116: =SUM(G95:G115) -> 0
C119: 2,3- Soc. Controlada, Controlante y Vinculada | G119: =+G143 -> 0
D121: # | E121: Nombre y Apellido, Denominación o Razón Social | F121: N° C.U.I.T. | G121: SALDO AL CIERRE
D122: 1
D123: 2
D124: 3
D125: 4
D126: 5
D127: 6
D128: 7
D129: 8
D130: 9
D131: 10
D132: 11
D133: 12
... D142: 21
D143: TOTAL DEUDAS CON SOCIEDADES VINCULADAS, CONTROLADAS Y/O CONTROLANTES | G143: =SUM(G122:G142) -> 0
C146: 2,4- Cuentas Particulares de Socios | G146: =+G170 -> 0
D148: # | E148: Nombre y Apellido, Denominación o Razón Social | F148: N° C.U.I.T. | G148: SALDO AL CIERRE
D149: 1
D150: 2
D151: 3
D152: 4
D153: 5
D154: 6
D155: 7
D156: 8
D157: 9
D158: 10
...

Sheet PATRIMONIO
B2: TOTAL PATRIMONIO s/detalle | D2: SUM I | F2: =+F4+F6+F8+F10+F12 -> 0 | I2: Control
I3: =+F2-F15 -> 0
D4: 3,1- Capital
D6: 3,2- Reserva Legal
D8: 3,3- Reserva por Revalúo Técnico
D10: 3,4- Otras Reservas
D12: 3,5- Resultados
C15: EVOLUCION DEL PATRIMONIO | F15: =+F17+F19-F21+F42+F56 -> 0
D17: 3,6 Patrimonio al inicio | F17: 0
D19: 3,7 Resultado contable del ejercicio | F19: 0
D21: 3,8 Disminuciones | F21: =F23+F25+F27+F34 -> 0
D23: 3,8,1 Reducción de capital | F23: 0
D25: 3,8,2 Otros | F25: 0
D27: 3,8,3 Honorarios | F27: =+F32 -> 0
D29: Nombre y Apellido, Denominación | E29: N° C.U.I.T. | F29: Importe
D32: TOTAL HONORARIOS | F32: =SUM(F30:F31) -> 0
D34: 3,8,4 Dividendos en efectivo / en especie | F34: =+F39 -> 0
D36: Nombre y Apellido, Denominación | E36: N° C.U.I.T. | F36: Importe
D39: TOTAL | F39: =SUM(F37:F38) -> 0
D42: 3,9 Aumentos | F42: =+F44+F51+F53 -> 0
D44: 3,9,1 Aportes | F44: =+F49 -> 0
D46: Nombre y Apellido, Denominación | E46: N° C.U.I.T. | F46: Importe
D49: TOTAL | F49: =SUM(F48:F48) -> 0
D51: 3,9,2 Capitalizaciones | F51: 0
D53: 3,9,3 Otros | F53: 0
D56: 3,10 Ajustes de ejercicios anteriores | F56: =+F58-F60 -> 0
D58: 3,10,1 Ganancias | F58: 0
D60: 3,10,1 Pérdidas | F60: 0

Sheet RESULTADOS
B2: TOTAL RESULTADOS s/detalle | C2: SUM I | D2: =SUM(D4,D23,D51,D62,D78,D81,D89,D91,D102,D112,D116)-D114 -> 0
B4: 4,1- Total Ventas, Serv.y Locac. | D4: =+D6+D12+D10+D16+D8+D14+D18+D20 -> 0 | E4: I
B6: Ventas Gravadas en el mercado local a sujetos vinculados | D6: 0
B8: Ventas exentas en el mercado local | D8: 0
B10: Total de exportaciones a sujetos radicados o a jurisdicciones de baja o nula imposicion | D10: 0
B12: Total de exportaciones exentas | D12: 0
B14: Otras ventas gravadas en el mercado local | D14: 0
B16: Total de exportaciones a sujetos vinculados sin detraer derechos de exportacion | D16: 0
B18: Total de otras exportaciones | D18: 0
B20: Derechos de Exportación | D20: 0
B23: 4,2- Costo Total | D23: =-(+D25+D27+D29+D31-D49) -> 0 | E23: I
B25: Existencia inicial | D25: 0
B27: Compras netas | D27: 0
B29: Gastos de producción
B31: Gastos vinculados al costo | D31: =+SUM(D33:D38) -> 0
B33: 1- Honorarios y retribuciones por servicios
B34: 2- Sueldos, aguinaldos, gratificaciones y contribuciones del personal comprendido en el convenio colectivo de trabajo
B35: 3- Sueldos, aguinaldos, gratificaciones y contribuciones del personal no comprendido en el convenio colectivo de trabajo
B36: 4- Depreciaciones de Bienes de uso
B38: 5- Otros gastos vinculados al costo | D38: =+SUM(D40:D47) -> 0
B40: 5-1 Servicios públicos - Energia eléctrica
B41: 5-2 Servicios públicos - Gas
B42: 5-3 Servicios públicos - Agua
B43: 5-4 Servicios públicos - Telefonía
B44: 5-5 Seguros
B45: 5-6 Gastos de combustible
B46: 5-7 Propaganda, Publicidad y Merchandising
B47: 5-8 Otros
B49: Existencia final | D49: 0
B51: 4,3- Total Cargo por Deudores Incobrables | D51: =-C59 -> 0 | E51: I
B53: NOTA: En caso de corresponder a cargos por incobrabilidad globales, se informa a través un una CUIT genérica: 30-00000000-7
B56: N° C.U.I.T. | C56: Importe
C59: =+SUM(C57:D58) -> 0
B62: 4,4- Total Otros Gastos operativos | D62: =-SUM(D64,D66,D68,D70,D72,D74,D76) -> 0 | E62: I
B64: Honorarios y retribuciones por servicios
B66: Honorarios a directores
B68: Sueldos, aguinaldos, gratificaciones y contribuciones del personal comprendido dentro del convenio colectivo de trabajo
B70: Sueldos, aguinaldos, gratificaciones y contribuciones del personal no comprendido dentro del convenio colectivo de trabajo | D70: 0
B72: Gastos de representación
B74: Depreciación Bienes de uso
B76: Otros gastos operativos
B78: 4,5- Resultado por inversiones permanentes | D78: 0 | E78: I
B81: 4,6- Total Resultados financieros | D81: =+D83+D85+D87 -> 0 | E81: I
B83: Resultado por exposición a la inflación
B85: Diferencia de cambio | D85: 0
B87: Otros resultados financieros
B89: 4,7- Resultado por venta de acciones, cuotas, partic.soc., etc. | D89: 0 | E89: I
B91: 4,8- Total Otros ingresos | D91: =+D100 -> 0 | E91: I
B93: Descripcion del ingreso | D93: Importe
B100: TOTAL OTROS INGRESOS | D100: =+SUM(D94:D99) -> 0
B102: 4,9- Total Otros egresos | D102: =-D110 -> 0 | E102: I
B104: Concepto | D104: Importe
B110: TOTAL OTROS EGRESOS | D110: =+SUM(D105:D109) -> 0
B112: 4,10- Resultados extraordinarios | D112: 0 | E112: I
B114: 4,11- Impuesto a las ganancias | E114: I
B116: 4,12- Resultados por instrumentos financieros derivados | D116: =+Q124 -> 0 | E116: I
B118: Nro de orden | C118: Fecha de concertacion | D118: Tipo de contrato | E118: Origen / Destino | F118: Vigencia | G118: Cuit contraparte | H118: Otros gastos | I118: Mercado institucionado | J118: Monto de la concertacion | K118: Intención | L118: Fuente | M118: Resultado de la/las lidacion/es | N118: Prima | O118: Entrega de bienes | P118: Fecha de vencimiento | Q118: Resultado imputable al ejercicio
Q124: =+SUM(Q119:Q123) -> 0

Sheet Rtdo contable s.fuente
B3: Atribución del Resultado Contable Sgún la Fuente
E6: Fuente Argentina | G6: Fuente Extranjera | I6: Totales
I7: (Estado de Resultados)
D9: Resultado Final del Ejercicio | G9: =E38 -> 0 | I9: =RESULTADOS!D2 -> 0 | K9: (viene por default del mismo aplicativo, es el resultado que viene del balance)
D11: Resultado por Venta de Acciones
D13: Resultado por Contratos derivados
D15: Renta Gravada
D17: Renta Exenta
G20: CONTROL | I20: =(E9+G9)-I9 -> 0
B24: Apertura de la fuente extranjera por país
D27: Pais donde se obtuvo resuelto de fuente extranjera | E27: Resultado obtenido
D38: TOTAL | E38: =+SUM(E28:E37) -> 0

Sheet Fuente extranjera
B3: Afganistán
B4: Albania
B5: Alemania
B6: Anguila
B7: Antártida
B8: Antigua y Barbuda
B9: Antillas Holandesas / Neerlandesas
B10: Arabia Saudita
B11: Argelia
B12: Armenia
B13: Aruba
B14: Ascención
... B269: Zimbabwe / Zimbabue

Sheet Pagos a cuenta =>

Sheet IDyC DJ
A1: Provenientes de | B1: Importe Computado | C1: Periodo de la percepcion (AAAA/MM) | D1: CUIT del agente de percepción | E1: CUIT del titular de la cuenta | F1: CBU/CVU | G1: Impuesto | H1: Periodo (AAAA)

Sheet IDyC Anticipos
A1: Provenientes de | B1: Importe Computado | C1: Numero de anticipo | D1: Periodo de la percepcion (AAAA/MM) | E1: CUIT del agente de percepción | F1: CUIT del titular de la cuenta | G1: CBU/CVU | H1: Impuesto | I1: Periodo (AAAA)

Sheet RETEN. y PERC.
A1: CUIT Agente Ret./Perc. | B1: Denominación o Razón Social | C1: Impuesto | D1: Descripción Impuesto | E1: Régimen | F1: Descripción Régimen | G1: Fecha Ret./Perc. | H1: Número Certificado | I1: Descripción Operación | J1: Importe Ret./Perc. | K1: Número Comprobante | L1: Fecha Comprobante | M1: Descripción Comprobante | N1: Fecha Registración DJ Ag.Ret.

Sheet RETEN. Y PERC. SIMPLIFICADO
A1: Tipo de Operación | B1: CUIT del Agente de Percepción | C1: Numero de Certificado | D1: Fecha | E1: Régimen | F1: Importe
A2: =IF(OR(LEN('RETEN. y PERC.'!F2)=0,'RETEN. y PERC.'!F2=0),"",'RETEN. y PERC.'!F2) | B2: =IF(OR(LEN('RETEN. y PERC.'!A2)=0,'RETEN. y PERC.'!A2=0),"",'RETEN. y PERC.'!A2) | C2: =IF(OR(LEN('RETEN. y PERC.'!H2)=0,'RETEN. y PERC.'!H2=0),"",'RETEN. y PERC.'!H2) | D2: =IF(OR(LEN('RETEN. y PERC.'!N2)=0,'RETEN. y PERC.'!N2=0),"",'RETEN. y PERC.'!N2) | F2: =IF(OR(LEN('RETEN. y PERC.'!J2)=0,'RETEN. y PERC.'!J2=0),"",'RETEN. y PERC.'!J2)
A3: =IF(OR(LEN('RETEN. y PERC.'!F3)=0,'RETEN. y PERC.'!F3=0),"",'RETEN. y PERC.'!F3) | B3: =IF(OR(LEN('RETEN. y PERC.'!A3)=0,'RETEN. y PERC.'!A3=0),"",'RETEN. y PERC.'!A3) | C3: =IF(OR(LEN('RETEN. y PERC.'!H3)=0,'RETEN. y PERC.'!H3=0),"",'RETEN. y PERC.'!H3) | D3: =IF(OR(LEN('RETEN. y PERC.'!N3)=0,'RETEN. y PERC.'!N3=0),"",'RETEN. y PERC.'!N3) | F3: =IF(OR(LEN('RETEN. y PERC.'!J3)=0,'RETEN. y PERC.'!J3=0),"",'RETEN. y PERC.'!J3)
A4: =IF(OR(LEN('RETEN. y PERC.'!F4)=0,'RETEN. y PERC.'!F4=0),"",'RETEN. y PERC.'!F4) | B4: =IF(OR(LEN('RETEN. y PERC.'!A4)=0,'RETEN. y PERC.'!A4=0),"",'RETEN. y PERC.'!A4) | C4: =IF(OR(LEN('RETEN. y PERC.'!H4)=0,'RETEN. y PERC.'!H4=0),"",'RETEN. y PERC.'!H4) | D4: =IF(OR(LEN('RETEN. y PERC.'!N4)=0,'RETEN. y PERC.'!N4=0),"",'RETEN. y PERC.'!N4) | F4: =IF(OR(LEN('RETEN. y PERC.'!J4)=0,'RETEN. y PERC.'!J4=0),"",'RETEN. y PERC.'!J4)
A5: =IF(OR(LEN('RETEN. y PERC.'!F5)=0,'RETEN. y PERC.'!F5=0),"",'RETEN. y PERC.'!F5) | B5: =IF(OR(LEN('RETEN. y PERC.'!A5)=0,'RETEN. y PERC.'!A5=0),"",'RETEN. y PERC.'!A5) | C5: =IF(OR(LEN('RETEN. y PERC.'!H5)=0,'RETEN. y PERC.'!H5=0),"",'RETEN. y PERC.'!H5) | D5: =IF(OR(LEN('RETEN. y PERC.'!N5)=0,'RETEN. y PERC.'!N5=0),"",'RETEN. y PERC.'!N5) | F5: =IF(OR(LEN('RETEN. y PERC.'!J5)=0,'RETEN. y PERC.'!J5=0),"",'RETEN. y PERC.'!J5)
A6: =IF(OR(LEN('RETEN. y PERC.'!F6)=0,'RETEN. y PERC.'!F6=0),"",'RETEN. y PERC.'!F6) | B6: =IF(OR(LEN('RETEN. y PERC.'!A6)=0,'RETEN. y PERC.'!A6=0),"",'RETEN. y PERC.'!A6) | C6: =IF(OR(LEN('RETEN. y PERC.'!H6)=0,'RETEN. y PERC.'!H6=0),"",'RETEN. y PERC.'!H6) | D6: =IF(OR(LEN('RETEN. y PERC.'!N6)=0,'RETEN. y PERC.'!N6=0),"",'RETEN. y PERC.'!N6) | F6: =IF(OR(LEN('RETEN. y PERC.'!J6)=0,'RETEN. y PERC.'!J6=0),"",'RETEN. y PERC.'!J6)
A7: =IF(OR(LEN('RETEN. y PERC.'!F7)=0,'RETEN. y PERC.'!F7=0),"",'RETEN. y PERC.'!F7) | B7: =IF(OR(LEN('RETEN. y PERC.'!A7)=0,'RETEN. y PERC.'!A7=0),"",'RETEN. y PERC.'!A7) | C7: =IF(OR(LEN('RETEN. y PERC.'!H7)=0,'RETEN. y PERC.'!H7=0),"",'RETEN. y PERC.'!H7) | D7: =IF(OR(LEN('RETEN. y PERC.'!N7)=0,'RETEN. y PERC.'!N7=0),"",'RETEN. y PERC.'!N7) | F7: =IF(OR(LEN('RETEN. y PERC.'!J7)=0,'RETEN. y PERC.'!J7=0),"",'RETEN. y PERC.'!J7)
A8: =IF(OR(LEN('RETEN. y PERC.'!F8)=0,'RETEN. y PERC.'!F8=0),"",'RETEN. y PERC.'!F8) | B8: =IF(OR(LEN('RETEN. y PERC.'!A8)=0,'RETEN. y PERC.'!A8=0),"",'RETEN. y PERC.'!A8) | C8: =IF(OR(LEN('RETEN. y PERC.'!H8)=0,'RETEN. y PERC.'!H8=0),"",'RETEN. y PERC.'!H8) | D8: =IF(OR(LEN('RETEN. y PERC.'!N8)=0,'RETEN. y PERC.'!N8=0),"",'RETEN. y PERC.'!N8) | F8: =IF(OR(LEN('RETEN. y PERC.'!J8)=0,'RETEN. y PERC.'!J8=0),"",'RETEN. y PERC.'!J8)
A9: =IF(OR(LEN('RETEN. y PERC.'!F9)=0,'RETEN. y PERC.'!F9=0),"",'RETEN. y PERC.'!F9) | B9: =IF(OR(LEN('RETEN. y PERC.'!A9)=0,'RETEN. y PERC.'!A9=0),"",'RETEN. y PERC.'!A9) | C9: =IF(OR(LEN('RETEN. y PERC.'!H9)=0,'RETEN. y PERC.'!H9=0),"",'RETEN. y PERC.'!H9) | D9: =IF(OR(LEN('RETEN. y PERC.'!N9)=0,'RETEN. y PERC.'!N9=0),"",'RETEN. y PERC.'!N9) | F9: =IF(OR(LEN('RETEN. y PERC.'!J9)=0,'RETEN. y PERC.'!J9=0),"",'RETEN. y PERC.'!J9)
A10: =IF(OR(LEN('RETEN. y PERC.'!F10)=0,'RETEN. y PERC.'!F10=0),"",'RETEN. y PERC.'!F10) | B10: =IF(OR(LEN('RETEN. y PERC.'!A10)=0,'RETEN. y PERC.'!A10=0),"",'RETEN. y PERC.'!A10) | C10: =IF(OR(LEN('RETEN. y PERC.'!H10)=0,'RETEN. y PERC.'!H10=0),"",'RETEN. y PERC.'!H10) | D10: =IF(OR(LEN('RETEN. y PERC.'!N10)=0,'RETEN. y PERC.'!N10=0),"",'RETEN. y PERC.'!N10) | F10: =IF(OR(LEN('RETEN. y PERC.'!J10)=0,'RETEN. y PERC.'!J10=0),"",'RETEN. y PERC.'!J10)
A11: =IF(OR(LEN('RETEN. y PERC.'!F11)=0,'RETEN. y PERC.'!F11=0),"",'RETEN. y PERC.'!F11) | B11: =IF(OR(LEN('RETEN. y PERC.'!A11)=0,'RETEN. y PERC.'!A11=0),"",'RETEN. y PERC.'!A11) | C11: =IF(OR(LEN('RETEN. y PERC.'!H11)=0,'RETEN. y PERC.'!H11=0),"",'RETEN. y PERC.'!H11) | D11: =IF(OR(LEN('RETEN. y PERC.'!N11)=0,'RETEN. y PERC.'!N11=0),"",'RETEN. y PERC.'!N11) | F11: =IF(OR(LEN('RETEN. y PERC.'!J11)=0,'RETEN. y PERC.'!J11=0),"",'RETEN. y PERC.'!J11)
A12: =IF(OR(LEN('RETEN. y PERC.'!F12)=0,'RETEN. y PERC.'!F12=0),"",'RETEN. y PERC.'!F12) | B12: =IF(OR(LEN('RETEN. y PERC.'!A12)=0,'RETEN. y PERC.'!A12=0),"",'RETEN. y PERC.'!A12) | C12: =IF(OR(LEN('RETEN. y PERC.'!H12)=0,'RETEN. y PERC.'!H12=0),"",'RETEN. y PERC.'!H12) | D12: =IF(OR(LEN('RETEN. y PERC.'!N12)=0,'RETEN. y PERC.'!N12=0),"",'RETEN. y PERC.'!N12) | F12: =IF(OR(LEN('RETEN. y PERC.'!J12)=0,'RETEN. y PERC.'!J12=0),"",'RETEN. y PERC.'!J12)
A13: =IF(OR(LEN('RETEN. y PERC.'!F13)=0,'RETEN. y PERC.'!F13=0),"",'RETEN. y PERC.'!F13) | B13: =IF(OR(LEN('RETEN. y PERC.'!A13)=0,'RETEN. y PERC.'!A13=0),"",'RETEN. y PERC.'!A13) | C13: =IF(OR(LEN('RETEN. y PERC.'!H13)=0,'RETEN. y PERC.'!H13=0),"",'RETEN. y PERC.'!H13) | D13: =IF(OR(LEN('RETEN. y PERC.'!N13)=0,'RETEN. y PERC.'!N13=0),"",'RETEN. y PERC.'!N13) | F13: =IF(OR(LEN('RETEN. y PERC.'!J13)=0,'RETEN. y PERC.'!J13=0),"",'RETEN. y PERC.'!J13)
... A437: =IF(OR(LEN('RETEN. y PERC.'!F437)=0,'RETEN. y PERC.'!F437=0),"",'RETEN. y PERC.'!F437) | B437: =IF(OR(LEN('RETEN. y PERC.'!A437)=0,'RETEN. y PERC.'!A437=0),"",'RETEN. y PERC.'!A437) | C437: =IF(OR(LEN('RETEN. y PERC.'!H437)=0,'RETEN. y PERC.'!H437=0),"",'RETEN. y PERC.'!H437) | D437: =IF(OR(LEN('RETEN. y PERC.'!N437)=0,'RETEN. y PERC.'!N437=0),"",'RETEN. y PERC.'!N437) | F437: =IF(OR(LEN('RETEN. y PERC.'!J437)=0,'RETEN. y PERC.'!J437=0),"",'RETEN. y PERC.'!J437)

Sheet PERC NC Calculo de anticipos
A1: Numero de certificado | B1: Fecha de percepción (DD/MM/AAAA) | C1: Importe | D1: REGIMENES

Sheet OTROS
B2: Anticipos cancelados con cómputo de Bonos y Créditos Fiscales | D2: 0
B4: Total anticipos ingresados en efectivo o mediante débitos bancarios -excepto F. 515 y bonos CF Dto. 135/06-
B6: Total pagos RG 5110 - Cesión de transferencia de documentos de transporte - (Importador/Exportador) | D6: 0
B8: Pagos a cuenta "Regimen excepcional de ingreso - Art. 4 RG 3818" | D8: =+D15 -> 0
B10: Numero de contrato | C10: Fecha de pago a cuenta | D10: Importe
D15: =+SUM(D11:D14) -> 0
B17: Total anticipos RG 4498 - Art. 3° Punto 1) | D17: =+D24 -> 0
B19: CUIT de origen | C19: Fecha del certificado | D19: Monto del anticipo
D24: =+SUM(D20:D23) -> 0
B26: Saldo a favor del periodo anterior | D26: 0

Sheet Saldo Previo al Cómputo del Imp
B2: Diferimiento F. 518 | D2: 0
B4: Pago a cuenta impuesto a la ganancia mínima presunta | D4: =+D16 -> 0
B6: Pago a cuenta ley de promoción a la investigación | D6: 0
B8: Pago a cuenta impuesto sobre los combustibles líquidos | D8: 0
B10: Pago a Cuenta - Compraventa de Moneda Extranjera | D10: 0
B12: Pago a cuenta Fomento a las Inversiones Productivas Pymes. Ley N 27264 | D12: =D19 -> 0
B14: Periodo de Origen | D14: Importe del pago a cuenta
B19: Total | D19: =+SUM(D15:E18) -> 0
B21: Otros pagos a cuenta | D21: 0

Sheet TAX=>

Sheet Ajustes Fuente Argentina
B2: TOTAL AJUSTES DE FUENTE ARGENTINA | D2: =+D4-D76 -> 0
B4: Ajustes Rdo. Impositivo de F.A. - aumentan utilidad o disminuyen pérdida | D4: =+D6+D13+D21+D30+D38+SUM(D52:D65)+SUM(D72:D74)+D71+D11 -> 0
B6: Instrumentos Financieros derivados | D6: =+D8+D9 -> 0
C8: Total Ajuste que disminuyen quebrantos | D8: 0
C9: Total Ajuste que incrementan utilidades | D9: 0
B11: Total de Ajustes por explotación de juegos de azar que aumentan utilidades y/o disminuyen quebrantos | D11: 0
B13: Total amortizaciones y castigos en exceso | D13: =+D15+D16+D17+D18+D19 -> 0
C15: Bienes Muebles | D15: 0
C16: Bienes Inmuebles | D16: 0
C17: Bienes Inmateriales | D17: 0
C18: Bienes que no revisten el carácter de Bienes de Cambio
C19: Otros (Amortizaciones y Castigos en exceso) | D19: 0
B21: Total ajustes por diferencia de valuación | D21: =+SUM(D23:D28) -> 0
C23: Leasing Financiero | D23: 0
C24: Fondo Común de Inversión | D24: 0
C25: Acciones | D25: 0
C26: Bienes de Cambio | D26: 0
C27: Títulos Públicos | D27: 0
C28: Otros Ajustes por diferencias de valuación | D28: 0
B30: Otras Provisiones, Previsiones y reservas no deducibles o deducidas en exceso | D30: =+SUM(D32:D36) -> 0
C32: Incobrables
C33: Inversiones | D33: 0
C34: Bienes de Cambio (Provis.) | D34: 0
C35: Otras Previsiones
C36: Provisiones y reservas no deducibles o deducidas en exceso
B38: Devoluciones al Aporte a Sociedades de Garantía Recíproca deducido | D38: =+E44 -> 0
C40: Periodo fiscal en el que se dedujo | D40: Fecha de retiro/devolucion | E40: Importe | F40: Cuit de la sociedad de Garantía Recíproca | G40: Fecha del aporte
E44: =+SUM(E41:E43) -> 0 | AF44: Ley N° 26.509
B46: Ajustes Positivos por Regimenes de Emergencia | D46: =+SUM(D48) -> 0
C48: Importe
C49: Regimen | D49: Ley N° 26.509
B52: Gastos de mant. y funcion. De automóviles no deducibles
B53: Gastos no deducibles
B54: Ases. Técnico del exterior | D54: 0
B55: Honorarios directores | D55: 0
B56: Rvas. Matemáticas y similares en Compañía de Seguros | D56: 0
B57: Dif. De cambio en exceso | D57: 0
B58: Inv. De Capital ó mejoras permanentes | D58: 0
B59: Ajuste por precio de transferencia | D59: 0
B60: Impuesto a las ganancias | D60: 0
B61: Ajustes disminuyen Queb. Por Ventas de Acciones | D61: 0
B62: Ajustes que incrementan Utilidades por Venta de Acciones | D62: 0
B63: Ajustes que disminuyen Quebrantos por Instrumentos Financieros Derivados | D63: 0
B64: Aj. Incrementan utilidades por Instrum. Finan. Derivados | D64: 0
B65: Intereses | D65: 0
B66: Ajuste por inflación
C67: *Ajuste Estático | D67: 0
C68: *Ajuste Dinámico
C69: *Ajuste por Inflación (períodos anteriores)
C70: *Rdo. Ajuste por inflación contable
C71: Total Ajuste por Inflación | D71: =+SUM(D67:D70) -> 0
B72: Pérdidas extraordinarias | D72: 0
B73: Otros ajustes
B74: Ajuste NIIFF
B76: Ajustes Rdo. Impositivo de F.A. - disminuyen utilidad o aumentan pérdida | D76: =+D78+D83+D88+D89+D107+D116+D121+SUM(D132:D134)+SUM(D141:D145)+D140 -> 0
B78: Ventas de acciones | D78: =+D80+D81 -> 0
C80: Total Ajuste que aumentan quebrantos | D80: 0
C81: Total Ajuste que disminuyen utilidades | D81: 0
B83: Instrumentos Financieros derivados | D83: =+D85+D86 -> 0
C85: Total Ajuste que disminuyen utilidades | D85: 0
C86: Total Ajuste que incrementan quebrantos | D86: 0
B88: Total de Ajustes por explotación de juegos de azar que disminuyen utilidades y/o aumentan quebrantos | D88: 0
B89: Total amortizaciones y castigos en defecto | D89: =+D91+D92+D95+D96+D99+D100+D103+D104+D105 -> 0
C91: Bienes Muebles | D91: 0
C92: Bienes Muebles amortización acelerada | D92: 0
C93: Bienes Muebles amortización acelerada según Ley N° | D93: Ninguna Ley de amortización acelerada
C94: Otra Ley de amortizacion acelerada (Bienes Muebles) | D94: 0 | E94: Completar en caso de no corresponder con el desplegable
C95: Bienes Inmateriales | D95: 0
C96: Bienes Inmateriales amortización acelerada | D96: 0
C97: Bienes Inmateriales amortización acelerada según Ley N° | D97: Ninguna Ley de amortización acelerada
C98: Otra Ley de amortizacion acelerada (Bienes Inmateriales) | D98: 0 | E98: Completar en caso de no corresponder con el desplegable
C99: Bienes Inmuebles | D99: 0
C100: Bienes Inmuebles amortización acelerada | D100: 0
C101: Bienes Inmuebles amortización acelerada según Ley N° | D101: Ninguna Ley de amortización acelerada
C102: Otra Ley de amortizacion acelerada (Bienes Inmuebles) | D102: 0 | E102: Completar en caso de no corresponder con el desplegable
C103: Bienes que no revisten el carácter de Bienes de Cambio | D103: 0
C104: Otros (Amortizaciones y Castigos en defecto) | D104: 0
C105: % de amortizacion utilizado por Ley 24.196
B107: Total ajustes por diferencia de valuación de inventario | D107: =+SUM(D109:D114) -> 0
C109: Leasing Financiero | D109: 0
C110: Fondo Común de Inversión
C111: Acciones | D111: 0
C112: Bienes de Cambio | D112: 0
C113: Títulos Públicos
C114: Otros Ajustes por diferencias de valuación
B116: Aportes a instituciones de capital emprendedor | D116: =+D119 -> 0
C118: Periodo fiscal del aporte | E118: si no aplica, dejar en blanco
C119: Monto del aporte | D119: 0
B121: Aportes a sociedades de garantía recíproca | D121: =+D125 -> 0
C123: Cuit de la sociedad de garantia recíproca
C124: Fecha del aporte | E124: si no aplica, dejar en blanco
C125: Importe del aporte | D125: 0
B127: Ajustes Negativos por Regimenes de Emergencia | D127: =+SUM(D129) -> 0
C129: Importe | D129: 0
C130: Regimen
B132: Ajustes correlativos por precio de transferencia | D132: 0
B133: Deducciones Gastos Art. 12 Ley 21.196 | D133: 0
B134: Rentas exentas o no gravadas | D134: 0
B135: Ajuste por inflación
C136: *Ajuste Estático
...

Sheet Ajustes Fuente Extranjera
B2: TOTAL AJUSTES DE FUENTE EXTRANJERA | D2: =+D4-D52 -> 0
B4: Ajustes Rdo. Impositivo de F.E. - aumentan utilidad o disminuyen pérdida | D4: =+D6+D11+D13+D21+D30+SUM(D38:D50) -> 0
B6: Ventas de acciones | D6: =+D8+D9 -> 0
C8: Total Ajuste que disminuyen quebrantos | D8: 0
C9: Total Ajuste que incrementan utilidades | D9: 0
B11: Total de Ajustes por explotación de juegos de azar que aumentan utilidades y/o disminuyen quebrantos
B13: Total amortizaciones y castigos en exceso | D13: =+SUM(D15:D19) -> 0
C15: Bienes Muebles | D15: 0
C16: Bienes Inmuebles | D16: 0
C17: Bienes Inmateriales | D17: 0
C18: Bienes que no revisten el carácter de Bienes de Cambio | D18: 0
C19: Otros (Amortizaciones y Castigos en exceso) | D19: 0
B21: Total ajustes por diferencia de valuación | D21: =+SUM(D23:D28) -> 0
C23: Leasing Financiero | D23: 0
C24: Fondo Común de Inversión | D24: 0
C25: Acciones | D25: 0
C26: Bienes de Cambio | D26: 0
C27: Títulos Públicos | D27: 0
C28: Otros Ajustes por diferencias de valuación | D28: 0
B30: Otras Provisiones, Previsiones y reservas no deducibles o deducidas en exceso | D30: =+SUM(D32:D36) -> 0
C32: Incobrables | D32: 0
C33: Inversiones | D33: 0
C34: Bienes de Cambio (Provis.) | D34: 0
C35: Otras Previsiones | D35: 0
C36: Provisiones y reservas no deducibles o deducidas en exceso | D36: 0
B38: Gastos de mant. y funcion. De automóviles no deducibles | D38: 0
B39: Gastos no deducibles | D39: 0
B40: Asesoramiento Técnico del exterior | D40: 0
B41: Honorarios directores | D41: 0
B42: Inv. De Capital ó mejoras permanentes | D42: 0
B43: Diferencia de cambio en exceso | D43: 0
B44: Reservas matemáticas y similares en Compañía de Seguros | D44: 0
B45: Impuestos a las Ganancias | D45: 0
B46: Intereses | D46: 0
B47: Resultado por Exposición a la inflación (REI) | D47: 0
B48: Pérdidas extraordinarias | D48: 0
B49: Ajustes por precio de transferencia | D49: 0
B50: Otros ajustes | D50: 0
B52: Ajustes Rdo. Impositivo de F.E. - disminuyen utilidad o aumentan pérdida | D52: =+D54+D59+D61+D69+SUM(D78:D84) -> 0
B54: Ventas de acciones | D54: =+D56+D57 -> 0
C56: Total Ajuste que aumentan quebrantos | D56: 0
C57: Total Ajuste que disminuyen utilidades | D57: 0
B59: Total de Ajustes por explotación de juegos de azar que disminuyen utilidades y/o aumentan quebrantos
B61: Total amortizaciones y castigos en defecto | D61: =+SUM(D63:D67) -> 0
C63: Bienes Muebles | D63: 0
C64: Bienes Inmuebles | D64: 0
C65: Bienes Inmateriales | D65: 0
C66: Bienes que no revisten el carácter de Bienes de Cambio | D66: 0
C67: Otros (Amortizaciones y Castigos en exceso) | D67: 0
B69: Total ajustes por diferencia de valuación de inventario | D69: =+SUM(D71:D76) -> 0
C71: Leasing Financiero | D71: 0
C72: Fondo Común de Inversión | D72: 0
C73: Acciones | D73: 0
C74: Bienes de Cambio | D74: 0
C75: Títulos Públicos | D75: 0
C76: Otros Ajustes por diferencias de valuación | D76: 0
B78: Rentas exentas o no gravadas | D78: 0
B79: Ajustes correlativos por precios de transferencia | D79: 0
B80: Resultado por Exposición a la inflación (REI) | D80: 0
B81: Reservas matemáticas y similares en compañía de seguros | D81: 0
B82: Pérdidas extraordinarias | D82: 0
B83: Honorarios directores | D83: 0
B84: Otro ajuste | D84: 0

Sheet Resultado Socios
A2: DATOS A CARGAR
A7: Tiene resultado atribuible a los socios? | B7: Tipo Societario | C7: CUIT/CUIL | D7: Participacion % | E7: Impuesto Retenido | F7: Residencia Tributaria | G7: NIF | H7: Domicilio exterior | I7: Pais
A19: SI | B19: Local
A20: NO | B20: Exterior

Sheet Formulario Op Internacionales
C2: DATOS A CARGAR
M3: F.742
M4: F.743
M5: F.867
M6: F.969
M7: F.741
C9: Esta obligado a presentar

Sheet Quebrantos F.A.
A2: Periodo fiscal (AAAA) | B2: Proyecto | C2: Quebranto | G2: Quebranto Computable | K2: Quebranto Trasladable | O2: Quebranto Cedido
C3: Por venta de acciones | D3: Por instrumentos financieros derivados | E3: Resto | F3: Por explotación de Juegos de Azar | G3: Por venta de acciones | H3: Por instrumentos financieros derivados | I3: Resto | J3: Por explotación de Juegos de Azar | K3: Por venta de acciones | L3: Por instrumentos financieros derivados | M3: Resto | N3: Por explotación de Juegos de Azar | O3: Por venta de acciones | P3: Por instrumentos financieros derivados | Q3: Resto | R3: Por explotación de Juegos de Azar
K4: =+C4-G4 -> 0 | L4: =+D4-H4 -> 0 | M4: =+E4-I4 -> 0 | N4: =+F4-J4 -> 0

Sheet Quebrantos F.E.
A2: Periodo fiscal (AAAA) | B2: Quebranto Actualizado | E2: Quebranto Computable | H2: Quebranto Trasladable
B3: Por venta de acciones | C3: Resto | D3: Por explotación de Juegos de Azar | E3: Por venta de acciones | F3: Resto | G3: Por explotación de Juegos de Azar | H3: Por venta de acciones | I3: Resto | J3: Por explotación de Juegos de Azar
