Workbook
Name \a: #REF!
Name \P: #REF!
Name \P: #REF!
Name \P: #REF!
Name \U: #REF!
Name \U: #REF!
Name \U: #REF!
Name _1: #REF!
Name _2: #REF!
Name _3: #REF!
Name _4: #REF!
Name A: #REF!
Name A: #REF!
Name A: #REF!
Name A_impresión_IM: #REF!
Name Account_Balance: #REF!
Name ARA_Threshold: #REF!
Name ARP_Threshold: #REF!
Name AUS_P_L: #REF!
Name AUS_P_L: #REF!
Name AUS_P_L: #REF!
Name B: #REF!
Name B: #REF!
Name B: #REF!
Name BAL_SHEET: #REF!
Name BAL_SHEET: #REF!
Name BAL_SHEET: #REF!
Name C_: #REF!
Name C_: #REF!
Name C_: #REF!
Name CAPX_AR: #REF!
Name CAPX_AR: #REF!
Name CAPX_AR: #REF!
Name CERO: #REF!
Name CORP_OH: #REF!
Name CORP_OH: #REF!
Name CORP_OH: #REF!
Name CORP_OH_APRO: #REF!
Name CORP_OH_APRO: #REF!
Name CORP_OH_APRO: #REF!
Name COSTOS: [1]EMBARQUES!#REF!
Name D: #REF!
Name D: #REF!
Name D: #REF!
Name DC_VAR1: #REF!
Name DC_VAR1: #REF!
Name DC_VAR1: #REF!
Name DC_VAR2: #REF!
Name DC_VAR2: #REF!
Name DC_VAR2: #REF!
Name DEUDA: [1]EMBARQUES!#REF!
Name diferencias: #REF!
Name diferencias: #REF!
Name diferencias: #REF!
Name Difference: #REF!
Name directcost: #REF!
Name directcost: #REF!
Name directcost: #REF!
Name Disaggregations: #REF!
Name E: #REF!

Sheet INDICE 
B10: Compañía / Razón Social
B11: Descripción del Trabajo
B14: CONCEPTO | C14: AJUSTE
B16: Notas | C16: GAN - GMP / NOTAS
B17: Resumen de Ajustes Impuesto a la Ganancia Mínima Presunta | C17: GMP
B18: Apertura de Ganancia Mínima Presunta Acumulada | C18: GMP / 1
B19: Anticipos del Impuesto a la Ganancia Mínima Presunta | C19: GMP / 2
B20: Altas de Bienes de Uso no Computables | C20: GMP - 1
B21: Resumen de Ajustes Impuesto a las Ganancias | C21: GAN
B22: Quebrantos Acumulados | C22: GAN / 1
B23: Anticipos del Impuesto a la Ganancia | C23: GAN / 2
B24: Detalle de Retenciones y Percepciones Sufridas | C24: GAN / 3
B25: Otros Pagos a Cuenta | C25: GAN / 4
B26: Valuación Titulos públicos | C26: GAN - 1
... B56: Estado de Evolución del Patrimonio Neto | C56: EEPN

Sheet Instructivo
B2: Valuación de Fondos Comunes de Inversión (FCI) y Certificados de Participación de FF
B4: OBJETIVO TEMPLATE:
B5: Determinar la valuación impositiva de la tenencia de Fondos Comunes de Inversión.
B7: INSTRUCTIVO:
A8: 1. | B8: Completar la hoja "1. PEPS T&L DTT" informando:
B9: Tenencias iniciales de FCI al cierre del ejercicio anterior.
B10: Los movimientos del ejercicio (suscripciones, rescates, garantías, etc.).
A12: 2. | B12: Presionar el botón "Calcular".
B14: Automáticamente se generarán dos hojas:
B15: HOJA 1: "Resumen Tenencias DTT"
B16: Expone las tenencias al cierre valuadas a costo de adquisición (valuación impositiva).
B17: La herramienta no calcula el Ajuste Dinámico; el usuario debe incorporar los IPC correspondientes.
B19: HOJA 2: "Resumen Ventas DTT"
B20: Expone la actualización del costo de los FCI existentes al inicio y enajenados en el ejercicio-> Información utilizable para AXI Estático y Actualización del costo - Art. 106 LIG.

Sheet GAN 
B11: Compañía / Razón Social
B13: Resumen de Ajustes Impuesto a las Ganancias
E15: FUENTE ARGENTINA | I15: FUENTE
B16: CONCEPTO | C16: SI / SF | D16: REF | E16: ESPECIFICO | G16: IMPORTE | I16: ARGENTINA | J16: EXTRANJERA
B18: Resultado del Ejercicio (histórico) | D18: EEPN | G18: =+[30]EEPN!E37 -> 0
B20: Valuación Contable Fondos Comunes de Inversión | C20: SI | D20: GAN-2 | E20: =+'GAN - 2 '!E37 -> 6.3927441e+09
B21: Valuación Impositiva Fondos Comunes de Inversión | C21: SI | D21: GAN-2 | E21: =+'GAN - 2 '!E39 -> -6.2404087e+09
B22: Valuación Contable Fondos Comunes de Inversión | C22: SF | D22: GAN-2 | E22: =+'GAN - 2 '!E47 -> -1.3137291e+10
B23: Valuación Impositiva Fondos Comunes de Inversión | C23: SF | D23: GAN-2 | E23: =+'GAN - 2 '!E49 -> 1.297991e+10
B24: Actualización del Costo FCI | D24: GAN-2 | E24: =+'GAN - 2 '!E51 -> -80177954 | G24: =+SUM(E20:E24) -> -85223396
B27: Resultado impositivo | G27: =SUM(G18:G26) -> -85223396
B29: Quebrantos acumulados computables ejercicios anteriores | D29: GAN|1
B32: Resultado impositivo para el cálculo del impuesto
B34: Alícuota del impuesto
B37: Impuesto determinado | G37: =+G27*E34 -> 0 | I37: GAN|2
B39: Pago a cuenta IGMP de ejercicios anteriores | D39: GMP/1
B41: Retenciónes y Percepciones | D41: GAN|3
B43: Anticipos Impuesto a las Ganancias | D43: GAN|2
B45: Otros Pagos a Cuenta | D45: GAN|4
B47: Total a pagar/ (a favor)
B50: Cálculo de anticipos
B52: Impuesto determinado
B53: Retenciones / Percepciones sufridas
B54: Base de cálculo
B56: Anticipo extraordinario
B57: Anticipos regulares

Sheet GAN - 2 
B28: Compañía / Razón Social
B29: Descripción del Trabajo
B31: Fondos Comunes de Inversión
B34: Saldo Inicial
B35: CONCEPTO | D35: REF. | E35: IMPORTE
B37: Valuación contable | D37: GAN LY | E37: =+' Resumen Tenencias DTT'!O33 -> 6.3927441e+09
B39: Valuación Impositiva | D39: GAN LY | E39: =+' Resumen Tenencias DTT'!O31 -> -6.2404087e+09
B41: Saldo Inicial del Ajuste | D41: GAN LY | E41: =+E37+E39 -> 1.5233541e+08 | F41: [1]
B44: Saldo Final
B45: CONCEPTO | D45: REF. | E45: IMPORTE
B47: Valuación contable | D47: BS / IGJ | E47: =+' Resumen Tenencias DTT'!O37 -> -1.3137291e+10
B49: Valuación Impositiva | D49: 2. Resumen Tenencias DTT | E49: =+' Resumen Tenencias DTT'!O35 -> 1.297991e+10
B51: Actualización del Costo FCI | D51: 2. Resumen Tenencias DTT | E51: =+' Resumen Tenencias DTT'!O39 -> -80177954
B53: Saldo Final del Ajuste | E53: =+E47+E49+E51 -> -2.3755881e+08 | F53: [2]
E54: GAN
B57: Determinación del Resultado Impositivo de la Venta de FCI
B59: Resultados Contables
B61: Ajuste de Valuación FCI | C61: SI | D61: [1] | E61: =+E41 -> 1.5233541e+08
B62: Ajuste de Valuación FCI | C62: SF | D62: [2] | E62: =+E53 -> -2.3755881e+08
B64: Resultado Impositivo de la Venta | E64: =SUM(E59:E62) -> -85223396
D66: Control c/ "Resumen Tenencias DTT" | E66: =+E64-' Resumen Tenencias DTT'!O41 -> 0

Sheet 1. PEPS T&L DTT
B2: =+[6]Inicio!B2 -> FAURECIA SISTEMAS DE ESCAPE ARGENTINA S.A | O2: PEPS T&L DTT
B3: =+[6]Inicio!B3 -> 30-68837468-1
B4: =+[6]Inicio!B4 -> 2025 | D4: Mes de cierre: | E4: =[6]Inicio!E4 -> 12
B5: =+[6]Inicio!B5 -> Original
B6: Fondos Comunes de Inversion
B7: Analisis Stock, Valuación y Costo PEPS
B9: Saldo Inicial
B11: [1] | C11: [2] | D11: [3] | E11: [4] | F11: [5]
B12: Fecha (DD/MM/AAAA) | C12: Especie | D12: Cuotas Partes | E12: Monto total | F12: Precio Unitario
B13: 45433 | C13: Patagonia | D13: 247597 | E13: 31137492 | F13: 125.75876
B14: 45436 | C14: Patagonia | D14: 277412 | E14: 34999973 | F14: 126.16604
B15: 45600 | C15: Patagonia | D15: 4020288 | E15: 5.9999987e+08 | F15: 149.24301
B16: 45608 | C16: Patagonia | D16: 179556 | E16: 26999992 | F16: 150.37087
B17: 45649 | C17: Patagonia | D17: 1217256 | E17: 1.8999988e+08 | F17: 156.08868
B18: 45652 | C18: Patagonia | D18: 5751452 | E18: 8.9999997e+08 | F18: 156.48222
B19: 45652 | C19: Patagonia | D19: 1469815 | E19: 2.2999991e+08 | F19: 156.48222
B20: 45603 | C20: Citibank | D20: 1578689 | E20: 99766068 | F20: 63.195519
B21: 45617 | C21: Citibank | D21: 5351017.5 | E21: 3.4e+08 | F21: 63.539317
B22: 45617 | C22: Citibank | D22: 13359224 | E22: 8.55e+08 | F22: 64.000721
B23: 45623 | C23: Citibank | D23: 3962907 | E23: 2.55e+08 | F23: 64.346703
B24: 45629 | C24: Citibank | D24: 15457725 | E24: 1e+09 | F24: 64.692571
... B31: 45656 | C31: Adacap | D31: 11936246 | E31: 1.5176012e+08 | F31: 12.714225
B35: Valuacion impositiva inicial | D35: =SUM(D13:D33) -> 91378947 | E35: =SUM(E13:E33) -> 6.2404087e+09
B38: Movimientos | F38: No completar
B40: [1] | C40: [2] | D40: [3] | E40: [4] | F40: [5]
B41: Fecha (DD/MM/AAAA) | C41: Especie | D41: Cuotas Partes | E41: Monto total | F41: Precio Unitario
B42: 45659 | C42: Patagonia | D42: -3811318 | E42: -6.0000004e+08 | F42: 157.42587
B43: 45663 | C43: Adacap | D43: -413527.98 | E43: -5288936.4 | F43: 12.789791
B44: 45663 | C44: Citibank | D44: -14725738 | E44: -980000000
B45: 45664 | C45: Citibank | D45: 3002848.5 | E45: 200000000 | F45: 66.550145
B46: 45665 | C46: Citibank | D46: 12001938 | E46: 800000000 | F46: 66.655903
B47: 45666 | C47: Citibank | D47: -9893868.9 | E47: -660000000 | F47: 66.707979
B48: 45667 | C48: Citibank | D48: -3969430.9 | E48: -265000000 | F48: 66.760199
B49: 45670 | C49: Citibank | D49: -5005875 | E49: -335000000 | F49: 66.921367
B50: 45671 | C50: Citibank | D50: -447926.15 | E50: -30000000 | F50: 66.975326
B51: 45672 | C51: Citibank | D51: 2685330.6 | E51: 180000000 | F51: 67.030853
B52: 45673 | C52: Citibank | D52: -2086899.8 | E52: -140000000 | F52: 67.085156
B53: 45674 | C53: Patagonia | D53: -1254247 | E53: -2.0000006e+08 | F53: 159.45828
B54: 45677 | C54: Citibank | D54: -6537867.7 | E54: -440000000 | F54: 67.30023
B55: 45678 | C55: Citibank | D55: -6384213.6 | E55: -430000000 | F55: 67.353636
B56: 45679 | C56: Citibank | D56: -2670334.2 | E56: -180000000 | F56: 67.407292
... B309: 46021 | C309: Citibank | D309: 39684398 | E309: 3500000000 | F309: 88.19587

Sheet  Resumen Tenencias DTT
B2: =+[6]Inicio!B2 -> FAURECIA SISTEMAS DE ESCAPE ARGENTINA S.A
B3: =+[6]Inicio!B3 -> 30-68837468-1
B4: =+[6]Inicio!B4 -> 2025 | D4: Mes de cierre: | E4: =[6]Inicio!E4 -> 12
B5: =+[6]Inicio!B5 -> Original
B6: Fondos Comunes de Inversion
I28: Axi Dinámico - Cálculo incorporado a mano
B30: Resumen: | C30: Patagonia | F30: 212.38554 | J30: 10121.371
B31: Fecha | C31: Especie | D31: Suscripciones | E31: Tenencia | F31: Precio Unitario | G31: Monto Total | I31: IPC Origen | J31: Coeficiente | K31: AxI Dinámico | M31: Saldo Inicial Impositivo | N31: PEPS T&L DTT | O31: =-'1. PEPS T&L DTT'!$E$35 -> -6.2404087e+09
B32: 45959 | C32: Patagonia | D32: 4913388 | E32: 255028 | F32: 203.52555 | G32: 51904714 | I32: 9603.8623 | J32: 0.05389 | K32: =+G32*J32 -> 2797145.1
B33: 46000 | C33: Patagonia | D33: 1431645 | E33: 1431645 | F33: 209.54905 | G33: 2.9999985e+08 | I33: 10121.371 | J33: 0 | K33: =+G33*J33 -> 0 | M33: Saldo Inicial Contable | N33: GAN PY | O33: 6.3927441e+09
K34: =+SUM(K32:K33) -> 2797145.1
D35: Tenencias s/Detalle | E35: =SUMIF('1. PEPS T&L DTT'!$C$13:$C$31,C30,'1. PEPS T&L DTT'!$D$13:$D$31) + SUMIF('1. PEPS T&L DTT'!$C$42:$C$309,C30,'1. PEPS T&L DTT'!$D$42:$D$309) -> 1686673 | G35: =SUM(G32:G33) -> 3.5190457e+08 | M35: Saldo Final Impositivo | N35: =+H85 -> [1] | O35: =+G85 -> 1.297991e+10
D36: Tenencias al Cierre | E36: =SUM(E32:E33) -> 1686673
D37: Control | E37: =E35-E36 -> 0 | M37: Saldo Final Contable | N37: BS | O37: =-C88 -> -1.3137291e+10
B39: Valuación Contable Patagonia | C39: =+E35*F30 -> 3.5822495e+08 | M39: Actualizacion del costo | N39: Resumen Ventas DTT | O39: =-'Resumen Ventas DTT'!L332 -> -80177954
M41: Resumen del Ajuste | O41: =+SUM(O31:O39) -> -85223396
B43: Resumen: | C43: Adacap | F43: 17.296842 | J43: 10121.371
B44: Fecha | C44: Especie | D44: Suscripciones | E44: Tenencia | F44: Precio Unitario | G44: Monto Total | I44: IPC Origen | J44: Coeficiente | K44: AxI Dinámico
B45: 45959 | C45: Adacap | D45: 13776210 | E45: 10407048 | F45: 16.549016 | G45: 1.722264e+08 | I45: 9603.8623 | J45: 0.05389 | K45: =+G45*J45 -> 9281280.8
K46: =+K45 -> 9281280.8
D47: Tenencias s/Detalle | E47: =SUMIF('1. PEPS T&L DTT'!$C$13:$C$31,C43,'1. PEPS T&L DTT'!$D$13:$D$31) + SUMIF('1. PEPS T&L DTT'!$C$42:$C$309,C43,'1. PEPS T&L DTT'!$D$42:$D$309) -> 10407048 | G47: =SUM(G45:G45) -> 1.722264e+08
D48: Tenencias al Cierre | E48: =SUM(E45:E45) -> 10407048
D49: Control | E49: =E47-E48 -> 0
B51: Valuacion Contable Adacap | C51: =+E47*F43 -> 1.8000906e+08
B55: Resumen: | C55: Citibank | J55: 10121.371
B56: Fecha | C56: Especie | D56: Suscripciones | E56: Tenencia | F56: Precio Unitario | G56: Monto Total | I56: IPC Origen | J56: Coeficiente | K56: AxI Dinámico
B57: 46007 | C57: Citibank | D57: 3847908 | E57: 2548847.2 | F57: 87.580056 | G57: 2.2322818e+08 | I57: 10121.371 | J57: 0 | K57: =+G57*J57 -> 0
B58: 46010 | C58: Citibank | D58: 8836445.5 | E58: 8836445.5 | F58: 87.704949 | G58: 775000000 | I58: 10121.371 | J58: 0 | K58: =+G58*J58 -> 0
B59: 46017 | C59: Citibank | D59: 25450884 | E59: 25450884 | F59: 88.012661 | G59: 2240000000 | I59: 10121.371 | J59: 0 | K59: =+G59*J59 -> 0
B60: 46020 | C60: Citibank | D60: 8553504.3 | E60: 8553504.3 | F60: 88.151005 | G60: 754000000 | I60: 10121.371 | J60: 0 | K60: =+G60*J60 -> 0
B61: 46021 | C61: Citibank | D61: 9354179.5 | E61: 9354179.5 | F61: 88.19587 | G61: 825000000 | I61: 10121.371 | J61: 0 | K61: =+G61*J61 -> 0
B62: 46021 | C62: Citibank | D62: 39684398 | E62: 39684398 | F62: 88.19587 | G62: 3500000000 | I62: 10121.371 | J62: 0 | K62: =+G62*J62 -> 0
K63: =+SUM(K57:K62) -> 0
D64: Tenencias s/Detalle | E64: =SUMIF('1. PEPS T&L DTT'!$C$13:$C$31,C55,'1. PEPS T&L DTT'!$D$13:$D$31) + SUMIF('1. PEPS T&L DTT'!$C$42:$C$309,C55,'1. PEPS T&L DTT'!$D$42:$D$309) -> 94428258 | G64: =SUM(G57:G62) -> 8.3172282e+09
D65: Tenencias al Cierre | E65: =SUM(E57:E62) -> 94428258
D66: Control | E66: =E64-E65 -> 0
B68: Valuación Contable Citibank | C68: =+E64*F62 -> 8.3281824e+09
B73: Resumen: | C73: Ahorro Pesos | F73: 295.08345 | J73: 10121.371
B74: Fecha | C74: Especie | D74: Suscripciones | E74: Tenencia | F74: Precio Unitario | G74: Monto Total | I74: IPC Origen | J74: Coeficiente | K74: AxI Dinámico
B75: 45972 | C75: Ahorro Pesos | D75: 7142691.9 | E75: 1348364.9 | F75: 280.00648 | G75: 3.775509e+08 | I75: 9841.3581 | J75: 0.02845 | K75: =+J75*G75 -> 10741323
B76: 45978 | C76: Ahorro Pesos | D76: 1229425.9 | E76: 1229425.9 | F76: 283.87233 | G76: 349000000 | I76: 9841.3581 | J76: 0.02845 | K76: =+J76*G76 -> 9929050
B77: 45987 | C77: Ahorro Pesos | D77: 10466516 | E77: 10466516 | F77: 286.62834 | G77: 3000000000 | I77: 9841.3581 | J77: 0.02845 | K77: =+J77*G77 -> 85350000
B78: 45993 | C78: Ahorro Pesos | D78: 777989.23 | E78: 777989.23 | F78: 287.92172 | G78: 224000000 | I78: 10121.371 | J78: 0 | K78: =+J78*G78 -> 0
B79: 45995 | C79: Ahorro Pesos | D79: 651150.6 | E79: 651150.6 | F79: 288.71969 | G79: 188000000 | I79: 10121.371 | J79: 0 | K79: =+J79*G79 -> 0
K80: =+SUM(K75:K79) -> 1.0602037e+08
D81: Tenencias s/Detalle | E81: =SUMIF('1. PEPS T&L DTT'!$C$13:$C$31,C73,'1. PEPS T&L DTT'!$D$13:$D$31) + SUMIF('1. PEPS T&L DTT'!$C$42:$C$309,C73,'1. PEPS T&L DTT'!$D$42:$D$309) -> 14473446 | G81: =SUM(G75:G79) -> 4.1385509e+09
D82: Tenencias al Cierre | E82: =SUM(E75:E79) -> 14473446 | G82: 4.1383845e+09
D83: Control | E83: =E81-E82 -> 0 | G83: =+G81-G82 -> 166377.4
B85: Valuación Contable Ahorro Pesos | C85: =+E81*F73 -> 4.2708745e+09 | F85: Valuacion Impositiva | G85: =+G81+G64+G47+G35 -> 1.297991e+10 | H85: [1]
B87: Total Valuacion Contable s/detalle | C87: =+C85+C68+C51+C39 -> 1.3137291e+10 | F87: AxI Dinámico | G87: =+K34+K46+K63+K80 -> 1.180988e+08 | H87: AxI
B88: Valuación Contable s/bs | C88: 1.3137291e+10
C89: =+C87-C88 -> 0.077835083

Sheet Resumen Ventas DTT
B2: =+[6]Inicio!B2 -> FAURECIA SISTEMAS DE ESCAPE ARGENTINA S.A
B3: =+[6]Inicio!B3 -> 30-68837468-1
B4: =+[6]Inicio!B4 -> 2025 | D4: Mes de cierre: | E4: =[6]Inicio!E4 -> 12
B5: =+[6]Inicio!B5 -> Original
B6: Fondos Comunes de Inversion | D6: IPC al cierre | E6: {=INDEX('[6]IPC-Update'!C:C, MATCH(1, ('[6]IPC-Update'!B:B>=DATE($B$4-1, $E$4, 1))*('[6]IPC-Update'!B:B<=EOMONTH(DATE($B$4-1, $E$4, 1), 0)), 0))} -> 7694.0075
B26: Resumen Ventas (PEPS): | C26: Patagonia
B27: Fecha de Venta | C27: Especie | D27: Cantidad de Cuotas Partes | E27: Precio Unit. Venta | F27: Importe Venta (tramo) | G27: Costo Unit. PEPS | H27: Costo PEPS Total | I27: Margen Fiscal | J27: Fecha de Compra | K27: IPC Fecha de Compra | L27: AxI sobre Costos Actualizados
B28: 45659 | C28: Patagonia | D28: 247597 | E28: 157.42587 | F28: 38978172 | G28: 125.75876 | H28: 31137492 | I28: 7840680.7 | J28: 45433 | K28: 6073.7165 | L28: 8306577.6 | M28: =+YEAR(J28) -> 2024
B29: 45659 | C29: Patagonia | D29: 277412 | E29: 157.42587 | F29: 43671825 | G29: 126.16604 | H29: 34999973 | I29: 8671851.4 | J29: 45436 | K29: 6073.7165 | L29: 9336975.4 | M29: =+YEAR(J29) -> 2024
B30: 45659 | C30: Patagonia | D30: 3286309 | E30: 157.42587 | F30: 5.1735004e+08 | G30: 149.24301 | H30: 4.9045864e+08 | I30: 26891406 | J30: 45600 | K30: 7491.4314 | L30: 13262512 | M30: =+YEAR(J30) -> 2024
B31: 45674 | C31: Patagonia | D31: 733979 | E31: 159.45828 | F31: 1.1703903e+08 | G31: 149.24301 | H31: 1.0954123e+08 | I31: 7497792.9 | J31: 45600 | K31: 7491.4314 | L31: 2962108.9 | M31: =+YEAR(J31) -> 2024
B32: 45674 | C32: Patagonia | D32: 179556 | E32: 159.45828 | F32: 28631690 | G32: 150.37087 | H32: 26999992 | I32: 1631697.7 | J32: 45608 | K32: 7491.4314 | L32: 730107.89 | M32: =+YEAR(J32) -> 2024
B33: 45674 | C33: Patagonia | D33: 340712 | E33: 159.45828 | F33: 54329348 | G33: 156.08868 | H33: 53181287 | I33: 1148061.5 | J33: 45649 | K33: 7694.0075 | M33: =+YEAR(J33) -> 2024
B34: 45687 | C34: Patagonia | D34: 876544 | E34: 161.21972 | F34: 1.4131618e+08 | G34: 156.08868 | H34: 1.368186e+08 | I34: 4497580.6 | J34: 45649 | K34: 7694.0075 | M34: =+YEAR(J34) -> 2024
B35: 45687 | C35: Patagonia | D35: 773379 | E35: 161.21972 | F35: 1.2468395e+08 | G35: 156.48222 | H35: 1.2102006e+08 | I35: 3663883 | J35: 45652 | K35: 7694.0075 | M35: =+YEAR(J35) -> 2024
B36: 45693 | C36: Patagonia | D36: 1296415 | E36: 161.98522 | F36: 2.1000007e+08 | G36: 156.48222 | H36: 2.028659e+08 | I36: 7134176.9 | J36: 45652 | K36: 7694.0075 | M36: =+YEAR(J36) -> 2024
B37: 45694 | C37: Patagonia | D37: 801922 | E37: 162.11058 | F37: 1.3000004e+08 | G37: 156.48222 | H37: 1.2548653e+08 | I37: 4513508.1 | J37: 45652 | K37: 7694.0075 | M37: =+YEAR(J37) -> 2024
B38: 45695 | C38: Patagonia | D38: 1448515 | E38: 162.23518 | F38: 2.350001e+08 | G38: 156.48222 | H38: 2.2666684e+08 | I38: 8333256.1 | J38: 45652 | K38: 7694.0075 | M38: =+YEAR(J38) -> 2024
B39: 45722 | C39: Patagonia | D39: 1431221 | E39: 165.57727 | F39: 2.3697766e+08 | G39: 156.48222 | H39: 2.2396064e+08 | I39: 13017025 | J39: 45652 | K39: 7694.0075 | M39: =+YEAR(J39) -> 2024
B40: 45722 | C40: Patagonia | D40: 247754 | E40: 165.57727 | F40: 41022430 | G40: 156.48222 | H40: 38769096 | I40: 2253334.8 | J40: 45652 | K40: 7694.0075 | M40: =+YEAR(J40) -> 2024
B41: 45768 | C41: Patagonia | D41: 1222061 | E41: 171.4329 | F41: 2.0950146e+08 | G41: 156.48222 | H41: 1.9123082e+08 | I41: 18270639 | J41: 45652 | K41: 7694.0075 | M41: =+YEAR(J41) -> 2024
B42: 45768 | C42: Patagonia | D42: 527895 | E42: 171.4329 | F42: 90498569 | G42: 166.91756 | H42: 88114948 | I42: 2383620.9 | J42: 45733 | K42: 8353.3158 | M42: =+YEAR(J42) -> 2025
B43: 45771 | C43: Patagonia | D43: 430662 | E43: 171.80449 | F43: 73989665 | G43: 166.91756 | H43: 71885052 | I43: 2104613.1 | J43: 45733 | K43: 8353.3158 | M43: =+YEAR(J43) -> 2025
B44: 45771 | C44: Patagonia | D44: 50405 | E44: 171.80449 | F44: 8659805.3 | G44: 168.63406 | H44: 8500000 | I44: 159805.32 | J44: 45747 | K44: 8353.3158 | M44: =+YEAR(J44) -> 2025
... B73: 46014 | C73: Patagonia | D73: 9463 | E73: 211.36403 | F73: 2000137.9 | G73: 203.52555 | H73: 1925962.3 | I73: 74175.571 | J73: 45959 | K73: 9603.8623 | M73: =+YEAR(J73) -> 2025
D75: Total Vendido (Cant.) | E75: =SUM(D28:D73) -> 35388689 | K75: Total AxI sobre Costos Actualizados | L75: =SUM(L28:L73) -> 34598282 | M75: I
D76: Total Venta (Importe) | E76: =SUM(F28:F73) -> 6.3380614e+09
D77: Costo Total Ventas (PEPS) | E77: =SUM(H28:H73) -> 6.0597323e+09
D78: Margen Total | E78: =SUM(I28:I73) -> 2.7832908e+08
B81: Resumen Ventas (PEPS): | C81: Adacap
B82: Fecha de Venta | C82: Especie | D82: Cantidad de Cuotas Partes | E82: Precio Unit. Venta | F82: Importe Venta (tramo) | G82: Costo Unit. PEPS | H82: Costo PEPS Total | I82: Margen Fiscal | J82: Fecha de Compra | K82: IPC Fecha de Compra | L82: AxI sobre Costos Actualizados
B83: 45663 | C83: Adacap | D83: 413527.98 | E83: 12.789791 | F83: 5288936.4 | G83: 11.592081 | H83: 4793649.8 | I83: 495286.59 | J83: 45558 | K83: 7122.2421 | L83: 384828.69 | M83: 2024
B84: 45701 | C84: Adacap | D84: 3532732.4 | E84: 13.186145 | F84: 46583122 | G84: 11.592081 | H84: 40951720 | I84: 5631401.6 | J84: 45558 | K84: 7122.2421 | L84: 3287557 | M84: 2024
B85: 45701 | C85: Adacap | D85: 1493300.6 | E85: 13.186145 | F85: 19690878 | G85: 12.714225 | H85: 18986160 | I85: 704718.41 | J85: 45656 | K85: 7694.0075 | M85: 2024
B86: 45708 | C86: Adacap | D86: 139996.23 | E86: 13.25654 | F86: 1855865.6 | G86: 12.714225 | H86: 1779943.5 | I86: 75922.054 | J86: 45656 | K86: 7694.0075 | M86: 2024
B87: 45743 | C87: Adacap | D87: 10302949 | E87: 13.59967 | F87: 1.4011671e+08 | G87: 12.714225 | H87: 1.3099402e+08 | I87: 9122694.9 | J87: 45656 | K87: 7694.0075 | M87: 2024
B88: 45743 | C88: Adacap | D88: 38387243 | E88: 13.59967 | F88: 5.2205384e+08 | G88: 13.510903 | H88: 5.1864632e+08 | I88: 3407520.4 | J88: 45734 | K88: 8353.3158 | M88: 2025
B89: 45859 | C89: Adacap | D89: 2320620.5 | E89: 14.858462 | F89: 34480851 | G89: 13.510903 | H89: 31353678 | I89: 3127173 | J89: 45734 | K89: 8353.3158 | M89: 2025
B90: 45859 | C90: Adacap | D90: 7012962.9 | E90: 14.858462 | F90: 1.0420184e+08 | G90: 14.811605 | H90: 1.0387324e+08 | I90: 328606.4 | J90: 45855 | K90: 9023.973 | M90: 2025
B91: 45887 | C91: Adacap | D91: 3789377.6 | E91: 15.261521 | F91: 57831665 | G91: 14.811605 | H91: 56126764 | I91: 1704901.6 | J91: 45855 | K91: 9023.973 | M91: 2025
B92: 45887 | C92: Adacap | D92: 63546.065 | E92: 15.261521 | F92: 969809.6 | G92: 14.91272 | H92: 947644.67 | I92: 22164.931 | J92: 45863 | K92: 9023.973 | M92: 2025
B93: 45932 | C93: Adacap | D93: 6642138.7 | E93: 16.043753 | F93: 1.0656483e+08 | G93: 14.91272 | H93: 99052355 | I93: 7512478.1 | J93: 45863 | K93: 9023.973 | M93: 2025
B94: 45932 | C94: Adacap | D94: 1.4343552e+08 | E94: 16.043753 | F94: 2.301244e+09 | G94: 16.029033 | H94: 2.2991326e+09 | I94: 2111370.8 | J94: 45931 | K94: 9603.8623 | M94: 2025
B95: 45947 | C95: Adacap | D95: 12248658 | E95: 16.328319 | F95: 2e+08 | G95: 16.029033 | H95: 1.9633415e+08 | I95: 3665851.9 | J95: 45931 | K95: 9603.8623 | M95: 2025
B96: 45968 | C96: Adacap | D96: 282814.08 | E96: 16.683537 | F96: 4718339.2 | G96: 16.029033 | H96: 4533236.3 | I96: 185102.95 | J96: 45931 | K96: 9603.8623 | M96: 2025
... B98: 46021 | C98: Adacap | D98: 292.3435 | E98: 17.296844 | F98: 5056.62 | G98: 16.549016 | H98: 4837.9973 | I98: 218.62274 | J98: 45959 | K98: 9603.8623 | M98: 2025
D100: Total Vendido (Cant.) | E100: =SUM(D83:D98) -> 2.3343455e+08 | K100: Total AxI sobre Costos Actualizados | L100: =SUM(L83:L98) -> 3672385.7 | M100: I
D101: Total Venta (Importe) | E101: =SUM(F83:F98) -> 3.6018104e+09
D102: Costo Total Ventas (PEPS) | E102: =SUM(H83:H98) -> 3.5632618e+09
D103: Margen Total | E103: =SUM(I83:I98) -> 38548596
B106: Resumen Ventas (PEPS): | C106: Citibank
B107: Fecha de Venta | C107: Especie | D107: Cantidad de Cuotas Partes | E107: Precio Unit. Venta | F107: Importe Venta (tramo) | G107: Costo Unit. PEPS | H107: Costo PEPS Total | I107: Margen Fiscal | J107: Fecha de Compra | K107: IPC Fecha de Compra | L107: AxI sobre Costos Actualizados
B108: 45663 | C108: Citibank | D108: 1578689 | E108: 66.550145 | F108: 1.0506198e+08 | G108: 63.195519 | H108: 99766068 | I108: 5295911 | J108: 45603 | K108: 7491.4314 | L108: 2697778.3 | M108: =+YEAR(J108) -> 2024
B109: 45663 | C109: Citibank | D109: 5351017.5 | E109: 66.550145 | F109: 3.5611099e+08 | G109: 63.539317 | H109: 3.4e+08 | I109: 16110993 | J109: 45617 | K109: 7491.4314 | L109: 9193953.8 | M109: =+YEAR(J109) -> 2024
B110: 45663 | C110: Citibank | D110: 7796031.5 | E110: 66.550145 | F110: 5.1882703e+08 | G110: 64.000721 | H110: 4.9895164e+08 | I110: 19875390 | J110: 45617 | K110: 7491.4314 | L110: 13492171 | M110: =+YEAR(J110) -> 2024
B111: 45666 | C111: Citibank | D111: 5563193 | E111: 66.707979 | F111: 3.7110936e+08 | G111: 64.000721 | H111: 3.5604836e+08 | I111: 15060999 | J111: 45617 | K111: 7491.4314 | L111: 9627918.2 | M111: =+YEAR(J111) -> 2024
B112: 45666 | C112: Citibank | D112: 3962907 | E112: 66.707979 | F112: 2.6435752e+08 | G112: 64.346703 | H112: 2.55e+08 | I112: 9357517.2 | J112: 45623 | K112: 7491.4314 | L112: 6895465.3 | M112: =+YEAR(J112) -> 2024
B113: 45666 | C113: Citibank | D113: 367768.92 | E113: 66.707979 | F113: 24533122 | G113: 64.692571 | H113: 23791917 | I113: 741204.43 | J113: 45629 | K113: 7694.0075 | M113: =+YEAR(J113) -> 2024
B114: 45667 | C114: Citibank | D114: 3969430.9 | E114: 66.760199 | F114: 265000000 | G114: 64.692571 | H114: 2.5679269e+08 | I114: 8207306.6 | J114: 45629 | K114: 7694.0075 | M114: =+YEAR(J114) -> 2024
B115: 45670 | C115: Citibank | D115: 5005875 | E115: 66.921367 | F115: 335000000 | G115: 64.692571 | H115: 3.2384293e+08 | I115: 11157074 | J115: 45629 | K115: 7694.0075 | M115: =+YEAR(J115) -> 2024
B116: 45671 | C116: Citibank | D116: 447926.15 | E116: 66.975326 | F116: 30000000 | G116: 64.692571 | H116: 28977494 | I116: 1022505.7 | J116: 45629 | K116: 7694.0075 | M116: =+YEAR(J116) -> 2024
B117: 45673 | C117: Citibank | D117: 2086899.8 | E117: 67.085156 | F117: 140000000 | G117: 64.692571 | H117: 1.3500691e+08 | I117: 4993085.2 | J117: 45629 | K117: 7694.0075 | M117: =+YEAR(J117) -> 2024
B118: 45677 | C118: Citibank | D118: 3579824.6 | E118: 67.30023 | F118: 2.4092302e+08 | G118: 64.692571 | H118: 2.3158805e+08 | I118: 9334961.7 | J118: 45629 | K118: 7694.0075 | M118: =+YEAR(J118) -> 2024
B119: 45677 | C119: Citibank | D119: 2958043.1 | E119: 67.30023 | F119: 1.9907698e+08 | G119: 65.135182 | H119: 1.9267268e+08 | I119: 6404305.4 | J119: 45637 | K119: 7694.0075 | M119: =+YEAR(J119) -> 2024
B120: 45678 | C120: Citibank | D120: 2875977.6 | E120: 67.353636 | F120: 1.9370755e+08 | G120: 65.135182 | H120: 1.8732732e+08 | I120: 6380223.9 | J120: 45637 | K120: 7694.0075 | M120: =+YEAR(J120) -> 2024
B121: 45678 | C121: Citibank | D121: 3508236.1 | E121: 67.353636 | F121: 2.3629245e+08 | G121: 65.407068 | H121: 2.2946343e+08 | I121: 6829020 | J121: 45642 | K121: 7694.0075 | M121: =+YEAR(J121) -> 2024
B122: 45679 | C122: Citibank | D122: 1537090.2 | E122: 67.407292 | F122: 1.0361109e+08 | G122: 65.407068 | H122: 1.0053657e+08 | I122: 3074524.8 | J122: 45642 | K122: 7694.0075 | M122: =+YEAR(J122) -> 2024
B123: 45679 | C123: Citibank | D123: 1133244 | E123: 67.407292 | F123: 76388910 | G123: 65.460653 | H123: 74182893 | I123: 2206017 | J123: 45643 | K123: 7694.0075 | M123: =+YEAR(J123) -> 2024
B124: 45680 | C124: Citibank | D124: 963514.02 | E124: 67.461395 | F124: 65000000 | G124: 65.460653 | H124: 63072257 | I124: 1927743 | J124: 45643 | K124: 7694.0075 | M124: =+YEAR(J124) -> 2024
... B315: 46014 | C315: Citibank | D315: 113795.21 | E315: 87.87716 | F315: 10000000 | G315: 87.580056 | H315: 9966191 | I315: 33809.013 | J315: 46007 | K315: 10121.371 | M315: =+YEAR(J315) -> 2025
M316: =+YEAR(J316) -> 1900
D317: Total Vendido (Cant.) | E317: =SUM(D108:D315) -> 5.1484309e+08 | K317: Total AxI sobre Costos Actualizados | L317: =SUM(L108:L315) -> 41907287 | M317: I
D318: Total Venta (Importe) | E318: =SUM(F108:F315) -> 3.975001e+10
D319: Costo Total Ventas (PEPS) | E319: =SUM(H108:H315) -> 3.8711539e+10
D320: Margen Total | E320: =SUM(I108:I315) -> 1.0384711e+09
B323: Resumen Ventas (PEPS): | C323: Ahorro Pesos
B324: Fecha de Venta | C324: Especie | D324: Cantidad de Cuotas Partes | E324: Precio Unit. Venta | F324: Importe Venta (tramo) | G324: Costo Unit. PEPS | H324: Costo PEPS Total | I324: Margen Fiscal | J324: Fecha de Compra | K324: IPC Fecha de Compra | L324: AxI sobre Costos Actualizados
B325: 45994 | C325: Ahorro Pesos | D325: 651744.79 | E325: 288.45647 | F325: 1.88e+08 | G325: 280.00648 | H325: 1.8249276e+08 | I325: 5507237 | J325: 45972 | K325: 9841.3581
B326: 46002 | C326: Ahorro Pesos | D326: 1721240.3 | E326: 290.4882 | F326: 5e+08 | G326: 280.00648 | H326: 4.8195844e+08 | I326: 18041561 | J326: 45972 | K326: 9841.3581 | M326: =+YEAR(J326) -> 2025
B327: 46009 | C327: Ahorro Pesos | D327: 3421341.9 | E327: 292.28297 | F327: 1e+09 | G327: 280.00648 | H327: 9.579979e+08 | I327: 42002101 | J327: 45972 | K327: 9841.3581 | M327: =+YEAR(J327) -> 2025
M328: =+YEAR(J328) -> 1900
D329: Total Vendido (Cant.) | E329: =SUM(D325:D327) -> 5794327.1 | K329: Total AxI sobre Costos Actualizados | L329: 0 | M329: I
D330: Total Venta (Importe) | E330: =SUM(F325:F327) -> 1.688e+09
D331: Costo Total Ventas (PEPS) | E331: =SUM(H325:H327) -> 1.6224491e+09
D332: Margen Total | E332: =SUM(I325:I327) -> 65550899 | G332: Valuacion Impositiva s/detalle | H332: =+SUMIF(M28:M327,"2024",H28:H327) -> 6.2404087e+09 | K332: Actualización del costo SUM I | L332: =+L329+L317+L100+L75 -> 80177954
G333: Valuacion Impositiva GAN PY | H333: =+'[6]GAN PY'!E61 -> 6.2404087e+09
H334: =+H332-H333 -> 0
