Workbook

Sheet Inicio
B2: CTF — Padrón Histórico de Bienes de Uso
B4: Impuesto a las Ganancias — Matching por código de Activo Fijo
B6: Configuración del ejercicio
B7: Año del ejercicio fiscal: | C7: 2025 | D7: Editá según el año a calcular
B8: Mes de cierre (1-12): | C8: 12 | D8: Default: 12 (diciembre)
B9: Fecha de cierre: | C9: =DATE(C7,C8,1) -> 45992 | D9: Derivado de año + mes
B10: IPC de cierre: | C10: =IFERROR(VLOOKUP(C8&"-"&C7,IPC!$A$2:$C$10000,3,FALSE()),"⚠ Falta IPC") -> 10121.4 | D10: IPC del mes de cierre del ejercicio
B12: Año LY: | C12: =C7-1 -> 2024 | D12: Derivado
B13: IPC de cierre LY: | C13: =IFERROR(VLOOKUP(C8&"-"&(C7-1),IPC!$A$2:$C$10000,3,FALSE()),"⚠ Falta IPC") -> 7694.0075 | D13: Mismo mes, año anterior
B16: Flujo de trabajo
B17: 1. Hoja IPC: pegá el último índice cuando salga. Todo se ajusta automáticamente.
B18: 2. Hoja Inputs: pegá los movimientos del año del cliente (4 columnas):
B19: A: Activo Fijo | B: Fecha Adq | C: VU | D: VO (positivo = alta, negativo = baja)
B20: 3. Apretá el botón CALCULAR. La macro va a:
B21: • Buscar cada código de Activo Fijo en la hoja CTF
B22: • Si EXISTE: sumar a la columna ALTA (si VO>0) o BAJA (si VO<0)
B23: • Si NO EXISTE: agregar línea nueva al padrón
B24: 4. Mirá la hoja Resumen para los totales y la hoja CTF para el detalle.
B26: 🟡 Amarillo: inputs del cliente
B27: 🟢 Verde: indicadores clave
B28: 🟠 Naranja: comparación año anterior
B29: 🔵 Azul: cálculos automáticos

Sheet Inputs
A1: 📋 INPUTS DEL CLIENTE — Pegá los movimientos del año (altas con VO+, bajas con VO-) | F1: ⬇️ Apretá CALCULAR (botón VBA — ver README)
A3: Activo Fijo | B3: Fecha Adquisición | C3: VU (años) | D3: VO (con signo)
F4: ℹ️ Reglas:
F5: • VO positivo = ALTA
F6: • VO negativo = BAJA
F7: • Activo Fijo existente → suma a su línea
F8: • Activo Fijo nuevo → agrega línea al CTF
F9: • Baja de activo inexistente → ERROR

Sheet CTF
A1: 🗂️ PADRÓN HISTÓRICO — Actualizado por el botón CALCULAR | E1: MOVIMIENTOS DEL AÑO | G1: CÁLCULOS HISTÓRICOS | M1: AJUSTE POR INFLACIÓN (AxI)
A2: Identificador | B2: Datos del bien | E2: Movimientos año | G2: VO al cierre | H2: Amortizaciones histórico | L2: Valor Residual | M2: IPC + Coef | P2: AxI | T2: Estado
A3: Activo Fijo | B3: Fecha Adq | C3: VU | D3: Valor Origen | E3: ALTA | F3: BAJA | G3: VO al cierre | H3: AA al inicio | I3: AE — Amort Ej. | J3: AB — Amort Baja | K3: AA al cierre | L3: VR al cierre | M3: IPC Alta | N3: IPC Cierre | O3: Coeficiente | P3: VO al cierre AxI | Q3: AA cierre AxI | R3: AE AxI | S3: VR AxI | T3: Estado
A4: 90006 | B4: 35582 | C4: 3 | D4: 198 | F4: -198 | G4: =IF(A4="","",D4+E4+F4) -> 0 | H4: 198 | I4: =IF(A4="","",IF(D4=0,0,IF(F4<=-D4,0,IF(YEAR(B4)+C4-1<ANIO_ACTUAL,0,IFERROR(G4/C4,0))))) -> 0 | J4: =IF(OR(A4="",F4=0,D4=0),0,H4*(F4/D4)) -> -198 | K4: =IF(A4="","",H4+I4+J4) -> 0 | L4: =IF(A4="","",G4-K4) -> 0 | M4: =IF(OR(A4="",YEAR(B4)<2018),0,IFERROR(VLOOKUP(MONTH(B4)&"-"&YEAR(B4),IPC!$A:$C,3,FALSE()),0)) -> 0 | N4: =IF(OR(A4="",YEAR(B4)<2018),0,IPC_CIERRE) -> 0 | O4: =IF(OR(A4="",M4=0),1,N4/M4) -> 1 | P4: =IF(A4="","",G4*O4) -> 0 | Q4: =IF(A4="","",K4*O4) -> 0 | R4: =IF(A4="","",I4*O4) -> 0 | S4: =IF(A4="","",P4-Q4) -> 0 | T4: =IF(A4="","",IF(YEAR(B4)=ANIO_ACTUAL,"ALTA "&ANIO_ACTUAL,IF(F4<>0,IF(F4<=-D4,"BAJA TOTAL","BAJA PARCIAL"),IF(YEAR(B4)+C4-1<ANIO_ACTUAL,"AGOTADA",IF(YEAR(B4)+C4-1=ANIO_ACTUAL,"ÚLTIMO AÑO","EN AMORTIZACIÓN"))))) -> BAJA TOTAL
A5: 130145 | B5: 40088 | C5: 3 | D5: 24295.04 | G5: =IF(A5="","",D5+E5+F5) -> 24295.04 | H5: 24295.04 | I5: =IF(A5="","",IF(D5=0,0,IF(F5<=-D5,0,IF(YEAR(B5)+C5-1<ANIO_ACTUAL,0,IFERROR(G5/C5,0))))) -> 0 | J5: =IF(OR(A5="",F5=0,D5=0),0,H5*(F5/D5)) -> 0 | K5: =IF(A5="","",H5+I5+J5) -> 24295.04 | L5: =IF(A5="","",G5-K5) -> 0 | M5: =IF(OR(A5="",YEAR(B5)<2018),0,IFERROR(VLOOKUP(MONTH(B5)&"-"&YEAR(B5),IPC!$A:$C,3,FALSE()),0)) -> 0 | N5: =IF(OR(A5="",YEAR(B5)<2018),0,IPC_CIERRE) -> 0 | O5: =IF(OR(A5="",M5=0),1,N5/M5) -> 1 | P5: =IF(A5="","",G5*O5) -> 24295.04 | Q5: =IF(A5="","",K5*O5) -> 24295.04 | R5: =IF(A5="","",I5*O5) -> 0 | S5: =IF(A5="","",P5-Q5) -> 0 | T5: =IF(A5="","",IF(YEAR(B5)=ANIO_ACTUAL,"ALTA "&ANIO_ACTUAL,IF(F5<>0,IF(F5<=-D5,"BAJA TOTAL","BAJA PARCIAL"),IF(YEAR(B5)+C5-1<ANIO_ACTUAL,"AGOTADA",IF(YEAR(B5)+C5-1=ANIO_ACTUAL,"ÚLTIMO AÑO","EN AMORTIZACIÓN"))))) -> AGOTADA
A6: 130146 | B6: 44905 | C6: 3 | D6: 39801.19 | G6: =IF(A6="","",D6+E6+F6) -> 39801.19 | H6: 26534.13 | I6: =IF(A6="","",IF(D6=0,0,IF(F6<=-D6,0,IF(YEAR(B6)+C6-1<ANIO_ACTUAL,0,IFERROR(G6/C6,0))))) -> 0 | J6: =IF(OR(A6="",F6=0,D6=0),0,H6*(F6/D6)) -> 0 | K6: =IF(A6="","",H6+I6+J6) -> 26534.13 | L6: =IF(A6="","",G6-K6) -> 13267.06 | M6: =IF(OR(A6="",YEAR(B6)<2018),0,IFERROR(VLOOKUP(MONTH(B6)&"-"&YEAR(B6),IPC!$A:$C,3,FALSE()),0)) -> 1134.5875 | N6: =IF(OR(A6="",YEAR(B6)<2018),0,IPC_CIERRE) -> 10121.4 | O6: =IF(OR(A6="",M6=0),1,N6/M6) -> 8.9207752 | P6: =IF(A6="","",G6*O6) -> 355057.47 | Q6: =IF(A6="","",K6*O6) -> 236705.01 | R6: =IF(A6="","",I6*O6) -> 0 | S6: =IF(A6="","",P6-Q6) -> 118352.46 | T6: =IF(A6="","",IF(YEAR(B6)=ANIO_ACTUAL,"ALTA "&ANIO_ACTUAL,IF(F6<>0,IF(F6<=-D6,"BAJA TOTAL","BAJA PARCIAL"),IF(YEAR(B6)+C6-1<ANIO_ACTUAL,"AGOTADA",IF(YEAR(B6)+C6-1=ANIO_ACTUAL,"ÚLTIMO AÑO","EN AMORTIZACIÓN"))))) -> AGOTADA
A7: 130147 | B7: 45184 | C7: 5 | D7: 36102.5 | E7: 10000 | G7: =IF(A7="","",D7+E7+F7) -> 46102.5 | H7: 7220.5 | I7: =IF(A7="","",IF(D7=0,0,IF(F7<=-D7,0,IF(YEAR(B7)+C7-1<ANIO_ACTUAL,0,IFERROR(G7/C7,0))))) -> 9220.5 | J7: =IF(OR(A7="",F7=0,D7=0),0,H7*(F7/D7)) -> 0 | K7: =IF(A7="","",H7+I7+J7) -> 16441 | L7: =IF(A7="","",G7-K7) -> 29661.5 | M7: =IF(OR(A7="",YEAR(B7)<2018),0,IFERROR(VLOOKUP(MONTH(B7)&"-"&YEAR(B7),IPC!$A:$C,3,FALSE()),0)) -> 2304.9242 | N7: =IF(OR(A7="",YEAR(B7)<2018),0,IPC_CIERRE) -> 10121.4 | O7: =IF(OR(A7="",M7=0),1,N7/M7) -> 4.3912073 | P7: =IF(A7="","",G7*O7) -> 202445.64 | Q7: =IF(A7="","",K7*O7) -> 72195.839 | R7: =IF(A7="","",I7*O7) -> 40489.127 | S7: =IF(A7="","",P7-Q7) -> 130249.8 | T7: =IF(A7="","",IF(YEAR(B7)=ANIO_ACTUAL,"ALTA "&ANIO_ACTUAL,IF(F7<>0,IF(F7<=-D7,"BAJA TOTAL","BAJA PARCIAL"),IF(YEAR(B7)+C7-1<ANIO_ACTUAL,"AGOTADA",IF(YEAR(B7)+C7-1=ANIO_ACTUAL,"ÚLTIMO AÑO","EN AMORTIZACIÓN"))))) -> EN AMORTIZACIÓN
A8: 200006 | B8: 36982 | C8: 26 | D8: 157005.79 | F8: -50000 | G8: =IF(A8="","",D8+E8+F8) -> 107005.79 | H8: 138543.13 | I8: =IF(A8="","",IF(D8=0,0,IF(F8<=-D8,0,IF(YEAR(B8)+C8-1<ANIO_ACTUAL,0,IFERROR(G8/C8,0))))) -> 4115.6073 | J8: =IF(OR(A8="",F8=0,D8=0),0,H8*(F8/D8)) -> -44120.389 | K8: =IF(A8="","",H8+I8+J8) -> 98538.348 | L8: =IF(A8="","",G8-K8) -> 8467.4415 | M8: =IF(OR(A8="",YEAR(B8)<2018),0,IFERROR(VLOOKUP(MONTH(B8)&"-"&YEAR(B8),IPC!$A:$C,3,FALSE()),0)) -> 0 | N8: =IF(OR(A8="",YEAR(B8)<2018),0,IPC_CIERRE) -> 0 | O8: =IF(OR(A8="",M8=0),1,N8/M8) -> 1 | P8: =IF(A8="","",G8*O8) -> 107005.79 | Q8: =IF(A8="","",K8*O8) -> 98538.348 | R8: =IF(A8="","",I8*O8) -> 4115.6073 | S8: =IF(A8="","",P8-Q8) -> 8467.4415 | T8: =IF(A8="","",IF(YEAR(B8)=ANIO_ACTUAL,"ALTA "&ANIO_ACTUAL,IF(F8<>0,IF(F8<=-D8,"BAJA TOTAL","BAJA PARCIAL"),IF(YEAR(B8)+C8-1<ANIO_ACTUAL,"AGOTADA",IF(YEAR(B8)+C8-1=ANIO_ACTUAL,"ÚLTIMO AÑO","EN AMORTIZACIÓN"))))) -> BAJA PARCIAL
A9: 300050 | B9: 45730 | C9: 5 | D9: 95432 | G9: =IF(A9="","",D9+E9+F9) -> 95432 | H9: 0 | I9: =IF(A9="","",IF(D9=0,0,IF(F9<=-D9,0,IF(YEAR(B9)+C9-1<ANIO_ACTUAL,0,IFERROR(G9/C9,0))))) -> 19086.4 | J9: =IF(OR(A9="",F9=0,D9=0),0,H9*(F9/D9)) -> 0 | K9: =IF(A9="","",H9+I9+J9) -> 19086.4 | L9: =IF(A9="","",G9-K9) -> 76345.6 | M9: =IF(OR(A9="",YEAR(B9)<2018),0,IFERROR(VLOOKUP(MONTH(B9)&"-"&YEAR(B9),IPC!$A:$C,3,FALSE()),0)) -> 8353.3158 | N9: =IF(OR(A9="",YEAR(B9)<2018),0,IPC_CIERRE) -> 10121.4 | O9: =IF(OR(A9="",M9=0),1,N9/M9) -> 1.2116626 | P9: =IF(A9="","",G9*O9) -> 115631.38 | Q9: =IF(A9="","",K9*O9) -> 23126.276 | R9: =IF(A9="","",I9*O9) -> 23126.276 | S9: =IF(A9="","",P9-Q9) -> 92505.105 | T9: =IF(A9="","",IF(YEAR(B9)=ANIO_ACTUAL,"ALTA "&ANIO_ACTUAL,IF(F9<>0,IF(F9<=-D9,"BAJA TOTAL","BAJA PARCIAL"),IF(YEAR(B9)+C9-1<ANIO_ACTUAL,"AGOTADA",IF(YEAR(B9)+C9-1=ANIO_ACTUAL,"ÚLTIMO AÑO","EN AMORTIZACIÓN"))))) -> ALTA 2025
A10: 300051 | B10: 45676 | C10: 2 | D10: 120000 | G10: =IF(A10="","",D10+E10+F10) -> 120000 | H10: 0 | I10: =IF(A10="","",IF(D10=0,0,IF(F10<=-D10,0,IF(YEAR(B10)+C10-1<ANIO_ACTUAL,0,IFERROR(G10/C10,0))))) -> 60000 | J10: =IF(OR(A10="",F10=0,D10=0),0,H10*(F10/D10)) -> 0 | K10: =IF(A10="","",H10+I10+J10) -> 60000 | L10: =IF(A10="","",G10-K10) -> 60000 | M10: =IF(OR(A10="",YEAR(B10)<2018),0,IFERROR(VLOOKUP(MONTH(B10)&"-"&YEAR(B10),IPC!$A:$C,3,FALSE()),0)) -> 7864.1257 | N10: =IF(OR(A10="",YEAR(B10)<2018),0,IPC_CIERRE) -> 10121.4 | O10: =IF(OR(A10="",M10=0),1,N10/M10) -> 1.2870344 | P10: =IF(A10="","",G10*O10) -> 154444.12 | Q10: =IF(A10="","",K10*O10) -> 77222.062 | R10: =IF(A10="","",I10*O10) -> 77222.062 | S10: =IF(A10="","",P10-Q10) -> 77222.062 | T10: =IF(A10="","",IF(YEAR(B10)=ANIO_ACTUAL,"ALTA "&ANIO_ACTUAL,IF(F10<>0,IF(F10<=-D10,"BAJA TOTAL","BAJA PARCIAL"),IF(YEAR(B10)+C10-1<ANIO_ACTUAL,"AGOTADA",IF(YEAR(B10)+C10-1=ANIO_ACTUAL,"ÚLTIMO AÑO","EN AMORTIZACIÓN"))))) -> ALTA 2025
G11: =IF(A11="","",D11+E11+F11) | I11: =IF(A11="","",IF(D11=0,0,IF(F11<=-D11,0,IF(YEAR(B11)+C11-1<ANIO_ACTUAL,0,IFERROR(G11/C11,0))))) | J11: =IF(OR(A11="",F11=0,D11=0),0,H11*(F11/D11)) -> 0 | K11: =IF(A11="","",H11+I11+J11) | L11: =IF(A11="","",G11-K11) | M11: =IF(OR(A11="",YEAR(B11)<2018),0,IFERROR(VLOOKUP(MONTH(B11)&"-"&YEAR(B11),IPC!$A:$C,3,FALSE()),0)) -> 0 | N11: =IF(OR(A11="",YEAR(B11)<2018),0,IPC_CIERRE) -> 0 | O11: =IF(OR(A11="",M11=0),1,N11/M11) -> 1 | P11: =IF(A11="","",G11*O11) | Q11: =IF(A11="","",K11*O11) | R11: =IF(A11="","",I11*O11) | S11: =IF(A11="","",P11-Q11) | T11: =IF(A11="","",IF(YEAR(B11)=ANIO_ACTUAL,"ALTA "&ANIO_ACTUAL,IF(F11<>0,IF(F11<=-D11,"BAJA TOTAL","BAJA PARCIAL"),IF(YEAR(B11)+C11-1<ANIO_ACTUAL,"AGOTADA",IF(YEAR(B11)+C11-1=ANIO_ACTUAL,"ÚLTIMO AÑO","EN AMORTIZACIÓN")))))
G12: =IF(A12="","",D12+E12+F12) | I12: =IF(A12="","",IF(D12=0,0,IF(F12<=-D12,0,IF(YEAR(B12)+C12-1<ANIO_ACTUAL,0,IFERROR(G12/C12,0))))) | J12: =IF(OR(A12="",F12=0,D12=0),0,H12*(F12/D12)) -> 0 | K12: =IF(A12="","",H12+I12+J12) | L12: =IF(A12="","",G12-K12) | M12: =IF(OR(A12="",YEAR(B12)<2018),0,IFERROR(VLOOKUP(MONTH(B12)&"-"&YEAR(B12),IPC!$A:$C,3,FALSE()),0)) -> 0 | N12: =IF(OR(A12="",YEAR(B12)<2018),0,IPC_CIERRE) -> 0 | O12: =IF(OR(A12="",M12=0),1,N12/M12) -> 1 | P12: =IF(A12="","",G12*O12) | Q12: =IF(A12="","",K12*O12) | R12: =IF(A12="","",I12*O12) | S12: =IF(A12="","",P12-Q12) | T12: =IF(A12="","",IF(YEAR(B12)=ANIO_ACTUAL,"ALTA "&ANIO_ACTUAL,IF(F12<>0,IF(F12<=-D12,"BAJA TOTAL","BAJA PARCIAL"),IF(YEAR(B12)+C12-1<ANIO_ACTUAL,"AGOTADA",IF(YEAR(B12)+C12-1=ANIO_ACTUAL,"ÚLTIMO AÑO","EN AMORTIZACIÓN")))))
G13: =IF(A13="","",D13+E13+F13) | I13: =IF(A13="","",IF(D13=0,0,IF(F13<=-D13,0,IF(YEAR(B13)+C13-1<ANIO_ACTUAL,0,IFERROR(G13/C13,0))))) | J13: =IF(OR(A13="",F13=0,D13=0),0,H13*(F13/D13)) -> 0 | K13: =IF(A13="","",H13+I13+J13) | L13: =IF(A13="","",G13-K13) | M13: =IF(OR(A13="",YEAR(B13)<2018),0,IFERROR(VLOOKUP(MONTH(B13)&"-"&YEAR(B13),IPC!$A:$C,3,FALSE()),0)) -> 0 | N13: =IF(OR(A13="",YEAR(B13)<2018),0,IPC_CIERRE) -> 0 | O13: =IF(OR(A13="",M13=0),1,N13/M13) -> 1 | P13: =IF(A13="","",G13*O13) | Q13: =IF(A13="","",K13*O13) | R13: =IF(A13="","",I13*O13) | S13: =IF(A13="","",P13-Q13) | T13: =IF(A13="","",IF(YEAR(B13)=ANIO_ACTUAL,"ALTA "&ANIO_ACTUAL,IF(F13<>0,IF(F13<=-D13,"BAJA TOTAL","BAJA PARCIAL"),IF(YEAR(B13)+C13-1<ANIO_ACTUAL,"AGOTADA",IF(YEAR(B13)+C13-1=ANIO_ACTUAL,"ÚLTIMO AÑO","EN AMORTIZACIÓN")))))

Sheet Resumen
B2: Resumen — CTF Histórico
B5: Año actual: | C5: =ANIO_ACTUAL -> 2025
B7: Padrón | C7: Cantidad
B8: Total de bienes en el padrón | C8: =COUNTA(tblCTF[Activo Fijo]) -> 7
B9: Bienes con ALTA este año | C9: =COUNTIF(tblCTF[ALTA],">0") -> 1
B10: Bienes con BAJA este año | C10: =COUNTIF(tblCTF[BAJA],"<0") -> 2
B11: Bienes nuevos del año actual | C11: =SUMPRODUCT((YEAR(tblCTF[Fecha Adq])=ANIO_ACTUAL)*1) -> 2
B12: Bienes que agotaron VU | C12: =COUNTIF(tblCTF[Estado],"AGOTADA") -> 2
B13: Bienes en último año de VU | C13: =COUNTIF(tblCTF[Estado],"ÚLTIMO AÑO") -> 0
B14: Bienes en amortización | C14: =COUNTIF(tblCTF[Estado],"EN AMORTIZACIÓN") -> 1
B17: Concepto | C17: Histórico | D17: Ajustado x Inflación
B18: Valor de Origen al cierre | C18: =SUM(tblCTF[VO al cierre]) -> 432636.52 | D18: =SUM(tblCTF[VO al cierre AxI]) -> 958879.44
B19: Altas del año | C19: =SUM(tblCTF[ALTA]) -> 10000
B20: Bajas del año | C20: =SUM(tblCTF[BAJA]) -> -50198
B21: AA al inicio del ejercicio | C21: =SUM(tblCTF[AA al inicio]) -> 196790.8
B22: AE — Amort. del Ejercicio | C22: =SUM(tblCTF[AE — Amort Ej.]) -> 92422.507 | D22: =SUM(tblCTF[AE AxI]) -> 144953.07
B23: AB — Amort. de Bajas | C23: =SUM(tblCTF[AB — Amort Baja]) -> -44318.389
B24: AA al cierre del ejercicio | C24: =SUM(tblCTF[AA al cierre]) -> 244894.92 | D24: =SUM(tblCTF[AA cierre AxI]) -> 532082.57
B25: VR al cierre | C25: =SUM(tblCTF[VR al cierre]) -> 187741.6 | D25: =SUM(tblCTF[VR AxI]) -> 426796.86

Sheet PG
B2: Prueba Global — Cuadratura de Amortización
B5: Verifica que la Amort. del Ejercicio cuadra desde sus componentes (Amort LY + altas − bajas − agotados LY)
B7: Ejercicio: | C7: =ANIO_ACTUAL -> 2025 | E7: Año LY: | F7: =ANIO_LY -> 2024
B9: Concepto | C9: Histórico | D9: Ajustado x Inflación
B10: (+) Amort. LY de bienes vivos en LY | C10: =SUMPRODUCT((tblCTF[Activo Fijo]<>"")*((IFERROR(YEAR(tblCTF[Fecha Adq]),0)<=ANIO_LY)*((IFERROR(YEAR(tblCTF[Fecha Adq]),0)+tblCTF[VU]-1)>=ANIO_LY))*IFERROR(tblCTF[Valor Origen]/tblCTF[VU],0)) -> 26526.248 | D10: =SUMPRODUCT((tblCTF[Activo Fijo]<>"")*((IFERROR(YEAR(tblCTF[Fecha Adq]),0)<=ANIO_LY)*((IFERROR(YEAR(tblCTF[Fecha Adq]),0)+tblCTF[VU]-1)>=ANIO_LY))*IFERROR(tblCTF[Valor Origen]/tblCTF[VU],0)*IFERROR(IF(tblCTF[IPC Alta]=0,1,tblCTF[IPC Cierre]/tblCTF[IPC Alta]),1)) -> 156097.89
B11: (+) Amort. ALTAS del año | C11: =SUMPRODUCT((tblCTF[Activo Fijo]<>"")*(IFERROR(YEAR(tblCTF[Fecha Adq]),0)=ANIO_ACTUAL)*IFERROR(tblCTF[Valor Origen]/tblCTF[VU],0))+SUMPRODUCT((tblCTF[Activo Fijo]<>"")*IFERROR(tblCTF[ALTA]/tblCTF[VU],0)) -> 81086.4 | D11: =SUMPRODUCT((tblCTF[Activo Fijo]<>"")*(IFERROR(YEAR(tblCTF[Fecha Adq]),0)=ANIO_ACTUAL)*IFERROR(tblCTF[Valor Origen]/tblCTF[VU],0)*IFERROR(IF(tblCTF[IPC Alta]=0,1,tblCTF[IPC Cierre]/tblCTF[IPC Alta]),1))+SUMPRODUCT((tblCTF[Activo Fijo]<>"")*IFERROR(tblCTF[ALTA]/tblCTF[VU],0)*IFERROR(IF(tblCTF[IPC Alta]=0,1,tblCTF[IPC Cierre]/tblCTF[IPC Alta]),1)) -> 109130.75
B12: (−) Amort. BAJAS del año | C12: =SUMPRODUCT((tblCTF[Activo Fijo]<>"")*(((IFERROR(YEAR(tblCTF[Fecha Adq]),0)<=ANIO_LY)*((IFERROR(YEAR(tblCTF[Fecha Adq]),0)+tblCTF[VU]-1)>=ANIO_LY))+(IFERROR(YEAR(tblCTF[Fecha Adq]),0)=ANIO_ACTUAL))*IFERROR(tblCTF[BAJA]/tblCTF[VU],0)) -> -1923.0769 | D12: =SUMPRODUCT((tblCTF[Activo Fijo]<>"")*(((IFERROR(YEAR(tblCTF[Fecha Adq]),0)<=ANIO_LY)*((IFERROR(YEAR(tblCTF[Fecha Adq]),0)+tblCTF[VU]-1)>=ANIO_LY))+(IFERROR(YEAR(tblCTF[Fecha Adq]),0)=ANIO_ACTUAL))*IFERROR(tblCTF[BAJA]/tblCTF[VU],0)*IFERROR(IF(tblCTF[IPC Alta]=0,1,tblCTF[IPC Cierre]/tblCTF[IPC Alta]),1)) -> -1923.0769
B13: (−) Amort. Bs. que agotaron VU en LY | C13: =-SUMPRODUCT((tblCTF[Activo Fijo]<>"")*((IFERROR(YEAR(tblCTF[Fecha Adq]),0)+tblCTF[VU]-1)=ANIO_LY)*IFERROR(tblCTF[Valor Origen]/tblCTF[VU],0)) -> -13267.063 | D13: =-SUMPRODUCT((tblCTF[Activo Fijo]<>"")*((IFERROR(YEAR(tblCTF[Fecha Adq]),0)+tblCTF[VU]-1)=ANIO_LY)*IFERROR(tblCTF[Valor Origen]/tblCTF[VU],0)*IFERROR(IF(tblCTF[IPC Alta]=0,1,tblCTF[IPC Cierre]/tblCTF[IPC Alta]),1)) -> -118352.49
B15: Amort. según PG (suma) | C15: =SUM(C10:C13) -> 92422.507 | D15: =SUM(D10:D13) -> 144953.07
B17: Amort. según CTF (Σ directo) | C17: =SUM(tblCTF[AE — Amort Ej.]) -> 92422.507 | D17: =SUM(tblCTF[AE AxI]) -> 144953.07
B19: Control (PG − CTF, debe ser 0) | C19: =C15-C17 -> 0 | D19: =D15-D17 -> 0 | E19: =IF(ABS(C19)<0.5,"✅ OK","❌ NO CUADRA") -> ✅ OK | F19: =IF(ABS(D19)<0.5,"✅ OK","❌ NO CUADRA") -> ✅ OK
B22: Cómo leer esta prueba:
B23: • La Amort. del año debe poder reconstruirse desde sus componentes: LY + altas − bajas − agotados LY.
B24: • Si Control = 0, el CTF está cuadrado: las amortizaciones se computan correctamente.
B25: • Si Control ≠ 0, hay un movimiento sin reflejar (o un error en VU, fechas, o saldos AA inicio).
B26: • Bienes pre-2018: no actualizan por inflación (coef = 1), aportan igual al histórico y al ajustado.
B27: • La PG ajustada incluye el AxI (diferencia ajustado vs histórico) embebido en cada componente.

Sheet IPC
A1: Mes-Año | B1: Fecha | C1: Índice IPC
A2: 12-2017 | B2: 43070 | C2: 124.7956
A3: 1-2018 | B3: 43101 | C3: 126.9887
A4: 2-2018 | B4: 43132 | C4: 130.0606
A5: 3-2018 | B5: 43160 | C5: 133.1054
A6: 4-2018 | B6: 43191 | C6: 136.7512
A7: 5-2018 | B7: 43221 | C7: 139.5893
A8: 6-2018 | B8: 43252 | C8: 144.8053
A9: 7-2018 | B9: 43282 | C9: 149.2966
A10: 8-2018 | B10: 43313 | C10: 155.1034
A11: 9-2018 | B11: 43344 | C11: 165.2383
A12: 10-2018 | B12: 43374 | C12: 174.1473
A13: 11-2018 | B13: 43405 | C13: 179.6388
... A102: 4-2026 | B102: 46113 | C102: 11363.09
